MCS8/iverilog-PIPE/rom.v
// **********
// COPYRIGHT(c) 2018, LUOYIN
// All rights reserved
// 
// IP LIB INDEX	: 
// IP Name		: BASIC
// File Name	: rom.v
// Module Name	: rom
// Full Name	: ROM
// 
// Author		: LUO YIN
// Email		: luoyin1986@gmail.com
// Data			: 2018/04/09
// Version		: 1.0
//
// Abstract		:
// Called By	: 
// 
// Modification Histroy
// 
// **********

// **********
// DEFINE MODEL PORT
// **********
//
module rom(
	ADDR_I,
	DAT_O
);

	// **********
	// DEFINE PARAMETER
	// **********

	// **********
	// DEFINE INPUT
	// **********
	input wire [13:0] ADDR_I;

	// **********
	// DEFINE OUTPUT
	// **********
	output reg [7:0] DAT_O;

	// **********
	// ATRRIBUTE
	// **********
	reg [7:0] mem[0:16383];

	// **********
	// INSTANCE MODULE
	// **********

	// **********
	// MAIN CODE
	// **********
	initial begin
		// $readmemh("rom.dat", mem);
		$readmemb("test1.bin", mem);
		end
	
	always @(ADDR_I) begin
		DAT_O <= mem[ADDR_I];
		end

endmodule

MCS8/iverilog-PIPE/cpu.v
// **********
// COPYRIGHT(c) 2018, LUOYIN
// All rights reserved
// 
// IP LIB INDEX	:
// IP Name		: 
// File Name	: 
// Module Name	: 
// Full Name	: 
// 
// Author		: 
// Email		: 
// Data			: 
// Version		: 
//
// Abstract		: 
// Called By	: 
// 
// Modification Histroy
// 
// Description
// F1->F2->F3->D->E->M->W
// **********

// **********
// DEFINE MODEL PORT
// **********
module cpu(
	// Clock
	CLK_I, nRST_I,
	// ICode
	I_DAT_I, I_ADDR_O,
	// DCode
	D_DAT_I, D_DAT_O, D_ADDR_O,
	// IO
	IO_DAT_I, IO_DAT_O, IO_ADDR_O
);

	// **********
	// DEFINE PARAMETER
	// **********

	// **********
	// DEFINE INPUT
	// **********
	// Clock
	input wire CLK_I, nRST_I;
	// ICode
	input wire [7:0] I_DAT_I;
	// DCode
	input wire [7:0] D_DAT_I;
	// IO
	input wire [7:0] IO_DAT_I;

	// **********
	// DEFINE OUTPUT
	// **********
	// ICode
	output wire [13:0] I_ADDR_O;
	// DCode
	output wire [7:0]  D_DAT_O;
	output wire [13:0] D_ADDR_O;
	// IO
	output wire [7:0]  IO_DAT_O;
	output wire [4:0]  IO_ADDR_O;
	
	// **********
	// ATRRIBUTE
	// **********
	// Stage F1
	reg [7:0] rF1_IR;
	reg rF1_IR_valid;
	// Stage F2
	reg [7:0] rF2_IR;
	reg rF2_IR_valid;
	// Stage F3
	reg [7:0] rF3_IR;
	reg rF3_IR_valid;
	// State D
	reg        	rD_valid;
	reg  [7:0] 	rD_icode;
	reg  [3:0] 	rD_ifun;
	reg  [2:0] 	rD_src;
	reg  [2:0] 	rD_dst;
	reg  [7:0] 	rD_valC;				// imm
	reg [13:0] 	rD_valP;
	reg  [1:0] 	rD_count;
	// ***** Stage E
	reg 		rE_valid;
	reg  [7:0] 	rE_icode;
	reg  [3:0] 	rE_ifun;
	reg  [2:0] 	rE_src;
	reg  [2:0] 	rE_dst;
	reg [13:0] 	rE_valP;
	reg [13:0] 	rE_addrM;
	reg  [4:0] 	rE_addrIO;
	// src
	reg  [7:0] 	rE_valC;				// imm
	reg  [7:0]	rE_valS;				// reg, input B of ALU
	reg  [7:0]	rE_valA;				// input A of ALU
	// ***** Stage M *****
	reg 		rM_valid;
	reg  [7:0] 	rM_icode;
	reg  [2:0] 	rM_dstR;
	reg  [7:0] 	rM_valC;				// imm
	reg  [7:0] 	rM_valS;				// reg
	reg  [7:0] 	rM_valE;				// alu
	wire		wM_dstM_CS;				// ->M
	wire		wM_dstM_CS_C;			// imm->M
	wire		wM_dstM_CS_S;			// reg->M
	reg [13:0] 	rM_valP;
	reg [13:0] 	rM_addrM;
	reg  [4:0] 	rM_addrIO;
	// Stage W
	reg 		rW_valid;
	reg  [7:0] 	rW_icode;
	reg  [2:0] 	rW_dstR;
	reg  [7:0] 	rW_valC;				// imm
	reg  [7:0] 	rW_valS;				// reg
	reg  [7:0] 	rW_valE;				// alu
	reg  [7:0] 	rW_valM;				// mem
	wire		wW_dstR_CS;				// ->reg
	wire		wW_dstR_CS_C;			// imm->reg
	wire		wW_dstR_CS_S;			// reg->reg
	wire		wW_dstR_CS_E;			// alu->reg
	wire		wW_dstR_CS_M;			// mem->reg
	reg [13:0] 	rW_valP;
	// Stack
	reg [13:0] rStack[7:0];
	reg [2:0] rStack_ndx;
	// RegBank
	reg [7:0] rRegBank[7:0];
	
	wire wDoubleByte;
	wire wTripleByte;
	
	wire wINS_NOP;
	
	// **********
	// INSTANCE MODULE
	// **********
	assign I_ADDR_O = rStack[rStack_ndx];
	assign wDoubleByte = (~rF3_IR[7])&(~rF3_IR[6])&( rF3_IR[2])&(~rF3_IR[0]);
	assign wTripleByte = (~rF3_IR[7])&( rF3_IR[6])&(~rF3_IR[0]);
	assign wSingle = (~wDoubleByte) & (~wTripleByte);
	assign wINS_NOP = (~rF3_IR[7])&(~rF3_IR[6])&(~rF3_IR[5])&(~rF3_IR[4])&(~rF3_IR[3])&(~rF3_IR[2])&(~rF3_IR[1]);
	
	// **** Stage M ****
	// src select
	// LMI
	assign wM_dstM_CS_C = (~rM_icode[7])&(~rM_icode[6])&(&rM_icode[5:3])&( rM_icode[2])&( rM_icode[1])&(~rM_icode[0]);		// LMI
	// LMr
	assign wM_dstM_CS_S = ( rM_icode[7])&( rM_icode[6])&(&rM_icode[5:3])&(~(&rM_icode[2:0]));								// LMr
	// dst control
	assign wM_dstM_CS = wM_dstM_CS_C | wM_dstM_CS_S;
	
	// **** Stage W ****
	// src select
	// LrI: 00DDD110
	assign wW_dstR_CS_C = (~rW_icode[7])&(~rW_icode[6])&(~(&rW_icode[5:3]))&( rW_icode[2])&( rW_icode[1])&(~rW_icode[0]);	// LrI
	// Lrr: 11DDDSSS
	assign wW_dstR_CS_S = ( rW_icode[7])&( rW_icode[6])&(~(&rW_icode[5:3]))&(~(&rW_icode[2:0]));							// Lrr
	// LrM: 11DDD111
	assign wW_dstR_CS_M = ( rW_icode[7])&( rW_icode[6])&(~(&rW_icode[5:3]))&(&rW_icode[2:0]);								// Lrr
	// INr/DCr/ALUr/ALUI/ROT
	// INr/DCr: 00DDD00x
	assign wW_dstR_CS_E = ( (~rW_icode[7]) & (~rW_icode[6]) & (~(&rW_icode[5:3])) & (~(|rW_icode[5:3])) & (~rW_icode[2]) & (~rW_icode[1]) ) |		// INr/DCr: 00DDD00x
						  ( ( rW_icode[7]) & (~rW_icode[6]) & (~(&rW_icode[2:0])) ) | 																// ALUr: 10PPPSSS
						  ( (~rW_icode[7]) & (~rW_icode[6]) & ( rW_icode[2]) & (~rW_icode[1]) & (~rW_icode[0]) ) |									// ALUI: 00PPP100
						  ( (~rW_icode[7]) & (~rW_icode[6]) & (~rW_icode[5]) & (~rW_icode[2]) & ( rW_icode[1]) & (~rW_icode[0]) );					// ROT:  000RR010
	// dst control
	assign wW_dstR_CS = wW_dstR_CS_C | wW_dstR_CS_S | wW_dstR_CS_M | wW_dstR_CS_E;
	
	// **********
	// MAIN CODE
	// **********
	// Stack Control
	always @(posedge CLK_I) begin
		if(~nRST_I) begin
			rStack[0] <= 14'b0;
			rStack[1] <= 14'b0;
			rStack[2] <= 14'b0;
			rStack[3] <= 14'b0;
			rStack[4] <= 14'b0;
			rStack[5] <= 14'b0;
			rStack[6] <= 14'b0;
			rStack[7] <= 14'b0;
			rStack_ndx <= 3'b0;
			end
		else begin
			rStack[rStack_ndx] <= rStack[rStack_ndx]+1;
			end
		end
		
	// Fetch 2 (F1->F2)
	always @(posedge CLK_I) begin
		if(~nRST_I) begin
			rF2_IR <= 8'b0;
			rF2_IR_valid <= 1'b0;
			end
		else begin
			rF2_IR <= rF1_IR;
			rF2_IR_valid <= rF1_IR_valid;
			end
		end
		
	// Fetch 3 (F2->F3)
	always @(posedge CLK_I) begin
		if(~nRST_I) begin
			rF3_IR <= 8'b0;
			rF3_IR_valid <= 8'b0;
			end
		else begin
			rF3_IR <= rF2_IR;
			rF3_IR_valid <= rF2_IR_valid;
			end
		end
		
	// Fetch (F3->D)
	always @(posedge CLK_I) begin
		if(~nRST_I) begin
			rD_valid <= 1'b0;
			rD_icode <= 8'b0;
			rD_ifun  <= 4'b0;
			rD_src   <= 3'b0;
			rD_dst   <= 3'b0;
			rD_valC  <= 8'b0;
			rD_valP  <= 14'b0;
			rD_count <= 2'b0;
			end
		else begin
			if((~rD_count[1])&(~rD_count[0])) begin
				rD_icode <= rF3_IR;
				rD_ifun  <= { (~rF3_IR[2])&( rF3_IR[1])&(~rF3_IR[0]), rF3_IR[5], rF3_IR[4], rF3_IR[3] };
				rD_src   <= rF3_IR[2:0];
				rD_dst   <= rF3_IR[5:3];
				rD_valC  <= rF2_IR;
				rD_valP  <= { rF1_IR[5:0], rF2_IR };
				rD_valid <= rF3_IR_valid & (~wINS_NOP);
				if(wDoubleByte)
					rD_count <= 1;
				else if(wTripleByte)
					rD_count <= 2;
				else
					rD_count <= 0;
				end
			else begin
				rD_count <= rD_count-1;
				rD_valid <= 1'b0;
				end
			end
		end
	
	// Decode (D->E)
	always @(posedge CLK_I) begin
		if(~nRST_I) begin
			rE_valid 		<= 1'b0;
			rE_icode 		<= 8'b0;
			rE_ifun  		<= 4'b0;
			rE_dst	 		<= 3'b0;
			rE_valP  		<= 14'b0;
			rE_valC  		<= 8'b0;
			end
		else begin
			rE_valid <= rD_valid;
			
			if(rD_valid) begin
				rE_icode 	<= rD_icode;
				rE_ifun  	<= rD_ifun;
				rE_src		<= rD_src;
				rE_dst  	<= rD_dst;
				rE_valP  	<= rD_valP;
				
				// valC
				rE_valC  <= rD_valC;
				
				// valA
				casex(rD_icode)
					5'b0000x: begin			// INr, DCr
						rE_valA <= rRegBank[rD_dst];
						end
					5'b00010: begin			// ROT
						rE_valA <= rRegBank[3'b000];
						end
					5'b00100: begin			// ALUI
						rE_valA <= rRegBank[3'b000];
						end
					5'b10xxx: begin			// ALUr
						rE_valA <= rRegBank[rD_src];
						end
					endcase
				
				// valS
				casex(rD_icode)
					5'b00000: begin
						rE_valS <= 8'b00000001;
						end
					5'b00001: begin
						rE_valS <= 8'b11111111;
						end
					5'b00100: begin
						rE_valS <= rD_valC;
						end
					5'b00110: begin
						rE_valS <= rD_valC;
						end
					default: begin
						rE_valS <= 8'b0;
						end
					endcase
				end
				
				// src select
				
			end
		end
		
	// Execute (E->M)
	always @(posedge CLK_I) begin
		if(~nRST_I) begin
			rM_valid 		<= 1'b0;
			rM_icode 		<= 8'b0;
			// src
			rM_valC			<= 8'b0;
			rM_valS			<= 8'b0;
			rM_valE			<= 8'b0;
			end
		else begin
			rM_valid		<= rE_valid;
			if(rE_valid) begin
				rM_icode	<= rE_icode;
				rM_valC		<= rE_valC;
				// dst control
				
				end
			end
		end
		
	// Memory (M->W)
	always @(posedge CLK_I) begin
		if(~nRST_I) begin
			rW_valid		<= 1'b0;
			rW_icode		<= 8'b0;
			// src
			rW_valC			<= 8'b0;
			rW_valS			<= 8'b0;
			rW_valE			<= 8'b0;
			rW_valM			<= 8'b0;
			end
		else begin
			rW_valid		<= rM_valid;
			if(rM_valid) begin
				rW_icode	<= rM_icode;
				end
			end
		end
	
	// WriteBack (ROM->F1)
	always @(posedge CLK_I) begin
		if(~nRST_I) begin
			rRegBank[0] <= 8'b0;
			rRegBank[1] <= 8'b0;
			rRegBank[2] <= 8'b0;
			rRegBank[3] <= 8'b0;
			rRegBank[4] <= 8'b0;
			rRegBank[5] <= 8'b0;
			rRegBank[6] <= 8'b0;
			rRegBank[7] <= 8'b0;
			rF1_IR <= 8'b0;
			rF1_IR_valid <=1'b0;
			end
		else begin
			rF1_IR <= I_DAT_I;
			rF1_IR_valid <= 1'b1;
			end
		end
	
endmodule

MCS8/iverilog-PIPE/bench_clock.v
// **********
// COPYRIGHT(c) 2018, LUOYIN
// All rights reserved
// 
// IP LIB INDEX	:
// IP Name		: 
// File Name	: 
// Module Name	: 
// Full Name	: 
// 
// Author		: 
// Email		: 
// Data			: 
// Version		: 
//
// Abstract		: 
// Called By	: 
// 
// Modification Histroy
// 
// **********

// **********
// DEFINE MODEL PORT
// **********
//
module bench_clock(
	CLK_O,
	nRST_O
);

	// **********
	// DEFINE PARAMETER
	// **********

	// **********
	// DEFINE INPUT
	// **********

	// **********
	// DEFINE OUTPUT
	// **********
	output reg CLK_O;
	output reg nRST_O;
	
	// **********
	// ATRRIBUTE
	// **********

	// **********
	// INSTANCE MODULE
	// **********

	// **********
	// MAIN CODE
	// **********
	initial begin
		CLK_O=1'b0;
		nRST_O=1'b1;
		forever #5 CLK_O=~CLK_O;
		end
		
	initial begin
		#100 nRST_O=1'b0;
		#100 nRST_O=1'b1;
		end
	
	initial begin
		#600 $finish;
		end
	
endmodule

MCS8/iverilog-PIPE/bench_top.v
// **********
// COPYRIGHT(c) 2018, LUOYIN
// All rights reserved
// 
// IP LIB INDEX	:
// IP Name		: 
// File Name	: 
// Module Name	: 
// Full Name	: 
// 
// Author		: 
// Email		: 
// Data			: 
// Version		: 
//
// Abstract		: 
// Called By	: 
// 
// Modification Histroy
// 
// **********

// **********
// DEFINE MODEL PORT
// **********
//
module bench_top();

	// **********
	// DEFINE PARAMETER
	// **********

	// **********
	// DEFINE INPUT
	// **********

	// **********
	// DEFINE OUTPUT
	// **********

	// **********
	// ATRRIBUTE
	// **********
	wire wCLK, wnRST;
	// ICODE
	wire [13:0] wI_ADDR;
	wire [7:0] wI_DAT;

	// **********
	// INSTANCE MODULE
	// **********
	bench_clock uClock(
		.CLK_O(wCLK), .nRST_O(wnRST)
	);
	cpu uCPU(
		.CLK_I(wCLK), .nRST_I(wnRST),
		.I_DAT_I(wI_DAT), .I_ADDR_O(wI_ADDR)
	);
	rom uRom(
		.ADDR_I(wI_ADDR),
		.DAT_O(wI_DAT)
	);

	// **********
	// MAIN CODE
	// **********
	initial begin
		$dumpvars(0, uClock);
		$dumpvars(0, uCPU);
		$dumpvars(0, uRom);
		end
	
endmodule

MCS8/iverilog-PIPE/dump.vcd
$date
	Thu Apr 19 16:22:06 2018
$end
$version
	Icarus Verilog
$end
$timescale
	1s
$end
$scope module bench_top $end
$scope module uClock $end
$var reg 1 ! CLK_O $end
$var reg 1 " nRST_O $end
$upscope $end
$upscope $end
$scope module bench_top $end
$scope module uCPU $end
$var wire 1 # CLK_I $end
$var wire 14 $ D_ADDR_O [13:0] $end
$var wire 8 % D_DAT_I [7:0] $end
$var wire 8 & D_DAT_O [7:0] $end
$var wire 5 ' IO_ADDR_O [4:0] $end
$var wire 8 ( IO_DAT_I [7:0] $end
$var wire 8 ) IO_DAT_O [7:0] $end
$var wire 14 * I_ADDR_O [13:0] $end
$var wire 8 + I_DAT_I [7:0] $end
$var wire 1 , nRST_I $end
$var wire 1 - wDoubleByte $end
$var wire 1 . wINS_NOP $end
$var wire 1 / wM_dstM_CS $end
$var wire 1 0 wM_dstM_CS_C $end
$var wire 1 1 wM_dstM_CS_S $end
$var wire 1 2 wSingle $end
$var wire 1 3 wTripleByte $end
$var wire 1 4 wW_dstR_CS $end
$var wire 1 5 wW_dstR_CS_C $end
$var wire 1 6 wW_dstR_CS_E $end
$var wire 1 7 wW_dstR_CS_M $end
$var wire 1 8 wW_dstR_CS_S $end
$var reg 2 9 rD_count [1:0] $end
$var reg 3 : rD_dst [2:0] $end
$var reg 8 ; rD_icode [7:0] $end
$var reg 4 < rD_ifun [3:0] $end
$var reg 3 = rD_src [2:0] $end
$var reg 8 > rD_valC [7:0] $end
$var reg 14 ? rD_valP [13:0] $end
$var reg 1 @ rD_valid $end
$var reg 3 A rE_dst [2:0] $end
$var reg 8 B rE_icode [7:0] $end
$var reg 4 C rE_ifun [3:0] $end
$var reg 3 D rE_src [2:0] $end
$var reg 8 E rE_valA [7:0] $end
$var reg 8 F rE_valC [7:0] $end
$var reg 14 G rE_valP [13:0] $end
$var reg 8 H rE_valS [7:0] $end
$var reg 1 I rE_valid $end
$var reg 8 J rF1_IR [7:0] $end
$var reg 1 K rF1_IR_valid $end
$var reg 8 L rF2_IR [7:0] $end
$var reg 1 M rF2_IR_valid $end
$var reg 8 N rF3_IR [7:0] $end
$var reg 1 O rF3_IR_valid $end
$var reg 8 P rM_icode [7:0] $end
$var reg 8 Q rM_valC [7:0] $end
$var reg 8 R rM_valE [7:0] $end
$var reg 8 S rM_valS [7:0] $end
$var reg 1 T rM_valid $end
$var reg 3 U rStack_ndx [2:0] $end
$var reg 8 V rW_icode [7:0] $end
$var reg 8 W rW_valC [7:0] $end
$var reg 8 X rW_valE [7:0] $end
$var reg 8 Y rW_valM [7:0] $end
$var reg 8 Z rW_valS [7:0] $end
$var reg 1 [ rW_valid $end
$upscope $end
$upscope $end
$scope module bench_top $end
$scope module uRom $end
$var wire 14 \ ADDR_I [13:0] $end
$var reg 8 ] DAT_O [7:0] $end
$upscope $end
$upscope $end
$enddefinitions $end
#0
$dumpvars
bx ]
bx \
x[
bx Z
bx Y
bx X
bx W
bx V
bx U
xT
bx S
bx R
bx Q
bx P
xO
bx N
xM
bx L
xK
bx J
xI
bx H
bx G
bx F
bx E
bx D
bx C
bx B
bx A
x@
bx ?
bx >
bx =
bx <
bx ;
bx :
bx 9
x8
x7
x6
x5
x4
x3
x2
x1
x0
x/
x.
x-
1,
bx +
bx *
bz )
bz (
bz '
bz &
bz %
bz $
0#
1"
0!
$end
#5
0@
1K
1!
1#
#10
0!
0#
#15
0I
1M
1!
1#
#20
0!
0#
#25
1O
0T
1!
1#
#30
0!
0#
#35
0[
1!
1#
#40
0!
0#
#45
1!
1#
#50
0!
0#
#55
1!
1#
#60
0!
0#
#65
1!
1#
#70
0!
0#
#75
1!
1#
#80
0!
0#
#85
1!
1#
#90
0!
0#
#95
1!
1#
#100
0!
0#
0"
0,
#105
b111110 ]
b111110 +
14
16
1.
12
0/
08
0-
03
00
01
05
07
b0 U
b0 *
b0 \
0M
b0 L
0O
b0 N
b0 9
b0 ?
b0 >
b0 :
b0 =
b0 <
b0 ;
b0 F
b0 G
b0 A
b0 C
b0 B
b0 R
b0 S
b0 Q
b0 P
b0 Y
b0 X
b0 Z
b0 W
b0 V
0K
b0 J
1!
1#
#110
0!
0#
#115
1!
1#
#120
0!
0#
#125
1!
1#
#130
0!
0#
#135
1!
1#
#140
0!
0#
#145
1!
1#
#150
0!
0#
#155
1!
1#
#160
0!
0#
#165
1!
1#
#170
0!
0#
#175
1!
1#
#180
0!
0#
#185
1!
1#
#190
0!
0#
#195
1!
1#
#200
0!
0#
1"
1,
#205
b1111 ]
b1111 +
b1 *
b1 \
1K
b111110 J
1!
1#
#210
0!
0#
#215
b1110 ]
b1110 +
b1111 J
b11111000000000 ?
1M
b111110 L
b10 *
b10 \
1!
1#
#220
0!
0#
#225
b10101010 ]
b10101010 +
02
1-
0.
b11 *
b11 \
b1111 L
1O
b111110 N
b111100111110 ?
b111110 >
b1110 J
1!
1#
#230
0!
0#
#235
b11110 ]
b11110 +
12
0-
b10101010 J
b1 9
1@
b111000001111 ?
b1111 >
b111 :
b110 =
b111 <
b111110 ;
b1111 N
b1110 L
b100 *
b100 \
1!
1#
#240
0!
0#
#245
b1010101 ]
b1010101 +
02
1-
b101 *
b101 \
b10101010 L
b1110 N
0@
b0 9
b0 H
b1111 F
b111000001111 G
b111 A
b110 D
b111 C
b111110 B
1I
b11110 J
1!
1#
#250
0!
0#
#255
b11000001 ]
b11000001 +
1/
10
12
0-
b1010101 J
b1111 Q
b111110 P
1T
0I
b1 9
1@
b1111010101010 ?
b10101010 >
b1 :
b1 <
b1110 ;
b10101010 N
b11110 L
b110 *
b110 \
1!
1#
#260
0!
0#
#265
b10000011 ]
b10000011 +
04
02
06
1-
05
b111 *
b111 \
b1010101 L
b11110 N
0@
b0 9
b10101010 F
b1111010101010 G
b1 A
b1 C
b1110 B
1I
0T
b111110 V
1[
b11000001 J
1!
1#
#270
0!
0#
#275
b11111111 ]
b11111111 +
0/
00
12
0-
b10000011 J
0[
b10101010 Q
b1110 P
1T
0I
b1 9
1@
b101010101 ?
b1010101 >
b11 :
b11 <
b11110 ;
b1010101 N
b11000001 L
b1000 *
b1000 \
1!
1#
#280
0!
0#
#285
bx ]
bx +
14
15
b1001 *
b1001 \
b10000011 L
b11000001 N
0@
b0 9
b1010101 F
b101010101 G
b11 A
b11 C
b11110 B
1I
0T
b1110 V
1[
b11111111 J
1!
1#
#290
0!
0#
#295
bx J
0[
b1010101 Q
b11110 P
1T
0I
1@
b11111110000011 ?
b10000011 >
b0 :
b1 =
b0 <
b11000001 ;
b10000011 N
b11111111 L
b1010 *
b1010 \
1!
1#
#300
0!
0#
#305
b1011 *
b1011 \
bx L
b11111111 N
bx11111111 ?
b11111111 >
b11 =
b10000011 ;
b10000011 F
b11111110000011 G
b0 A
b1 D
b0 C
b11000001 B
1I
0T
b11110 V
1[
1!
1#
#310
0!
0#
#315
x.
x2
x-
x3
0[
b10000011 Q
b11000001 P
1T
b11111111 F
bx11111111 G
b11 D
b10000011 B
bx ?
bx >
b111 :
b111 =
b111 <
b11111111 ;
bx N
b1100 *
b1100 \
1!
1#
#320
0!
0#
#325
06
18
05
b1101 *
b1101 \
x@
bx :
bx =
bx <
bx ;
bx F
bx G
b111 A
b111 D
b111 C
b11111111 B
b11111111 Q
b10000011 P
b11000001 V
1[
1!
1#
#330
0!
0#
#335
16
08
b10000011 V
bx Q
b11111111 P
xI
b1110 *
b1110 \
1!
1#
#340
0!
0#
#345
04
06
b1111 *
b1111 \
xT
b11111111 V
1!
1#
#350
0!
0#
#355
x[
b10000 *
b10000 \
1!
1#
#360
0!
0#
#365
b10001 *
b10001 \
1!
1#
#370
0!
0#
#375
b10010 *
b10010 \
1!
1#
#380
0!
0#
#385
b10011 *
b10011 \
1!
1#
#390
0!
0#
#395
b10100 *
b10100 \
1!
1#
#400
0!
0#
#405
b10101 *
b10101 \
1!
1#
#410
0!
0#
#415
b10110 *
b10110 \
1!
1#
#420
0!
0#
#425
b10111 *
b10111 \
1!
1#
#430
0!
0#
#435
b11000 *
b11000 \
1!
1#
#440
0!
0#
#445
b11001 *
b11001 \
1!
1#
#450
0!
0#
#455
b11010 *
b11010 \
1!
1#
#460
0!
0#
#465
b11011 *
b11011 \
1!
1#
#470
0!
0#
#475
b11100 *
b11100 \
1!
1#
#480
0!
0#
#485
b11101 *
b11101 \
1!
1#
#490
0!
0#
#495
b11110 *
b11110 \
1!
1#
#500
0!
0#
#505
b11111 *
b11111 \
1!
1#
#510
0!
0#
#515
b100000 *
b100000 \
1!
1#
#520
0!
0#
#525
b100001 *
b100001 \
1!
1#
#530
0!
0#
#535
b100010 *
b100010 \
1!
1#
#540
0!
0#
#545
b100011 *
b100011 \
1!
1#
#550
0!
0#
#555
b100100 *
b100100 \
1!
1#
#560
0!
0#
#565
b100101 *
b100101 \
1!
1#
#570
0!
0#
#575
b100110 *
b100110 \
1!
1#
#580
0!
0#
#585
b100111 *
b100111 \
1!
1#
#590
0!
0#
#595
b101000 *
b101000 \
1!
1#
