MCS8/iverilog-PIPE/rom.v
// **********
// COPYRIGHT(c) 2018, LUOYIN
// All rights reserved
// 
// IP LIB INDEX	: 
// IP Name		: BASIC
// File Name	: rom.v
// Module Name	: rom
// Full Name	: ROM
// 
// Author		: LUO YIN
// Email		: luoyin1986@gmail.com
// Data			: 2018/04/09
// Version		: 1.0
//
// Abstract		:
// Called By	: 
// 
// Modification Histroy
// 
// **********

// **********
// DEFINE MODEL PORT
// **********
//
module rom(
	ADDR_I,
	DAT_O
);

	// **********
	// DEFINE PARAMETER
	// **********

	// **********
	// DEFINE INPUT
	// **********
	input wire [13:0] ADDR_I;

	// **********
	// DEFINE OUTPUT
	// **********
	output reg [7:0] DAT_O;

	// **********
	// ATRRIBUTE
	// **********
	reg [7:0] mem[0:16383];

	// **********
	// INSTANCE MODULE
	// **********

	// **********
	// MAIN CODE
	// **********
	initial begin
		// $readmemh("rom.dat", mem);
		$readmemb("test1.bin", mem);
		end
	
	always @(ADDR_I) begin
		DAT_O <= mem[ADDR_I];
		end

endmodule

MCS8/iverilog-PIPE/cpu_forward.v
// **********
// COPYRIGHT(c) 2018, LUOYIN
// All rights reserved
// 
// IP LIB INDEX	:
// IP Name		:
// File Name	:
// Module Name	:
// Full Name	:
// 
// Author		: 
// Email		:
// Data			:
// Version		:
//
// Abstract		:
// Called By	: 
// 
// Modification Histroy
// 
// **********

// **********
// DEFINE MODEL PORT
// **********
//
module cpu_forward(
	REG_BANK_I, REG_SRC_I,
	M_VAL_C_I, M_VAL_S_I, M_VAL_E_I,
	W_VAL_C_I, W_VAL_S_I, W_VAL_E_I, W_VAL_M_I,
	M_DST_I, M_VALID_I, M_DSTR_CS_I, M_DSTR_CS_C_I, M_DSTR_CS_S_I, M_DSTR_CS_E_I,
	W_DST_I, W_VALID_I, W_DSTR_CS_I, W_DSTR_CS_C_I, W_DSTR_CS_S_I, W_DSTR_CS_E_I, W_DSTR_CS_M_I,
	REG_BANK_O
);

	// **********
	// DEFINE PARAMETER
	// **********

	// **********
	// DEFINE INPUT
	// **********
	input [7:0] 	REG_BANK_I;
	input [2:0] 	REG_SRC_I;
	input [7:0] 	M_VAL_C_I;
	input [7:0] 	M_VAL_S_I;
	input [7:0] 	M_VAL_E_I;
	input [7:0] 	W_VAL_C_I;
	input [7:0] 	W_VAL_S_I;
	input [7:0] 	W_VAL_E_I;
	input [7:0] 	W_VAL_M_I;
	input [2:0]		M_DST_I;
	input			M_VALID_I;
	input 			M_DSTR_CS_I;
	input			M_DSTR_CS_C_I;
	input			M_DSTR_CS_S_I;
	input			M_DSTR_CS_E_I;
	input [2:0]		W_DST_I;
	input			W_VALID_I;
	input 			W_DSTR_CS_I;
	input			W_DSTR_CS_C_I;
	input			W_DSTR_CS_S_I;
	input			W_DSTR_CS_E_I;
	input			W_DSTR_CS_M_I;

	// **********
	// DEFINE OUTPUT
	// **********
	output [7:0] 	REG_BANK_O;
	
	// **********
	// ATRRIBUTE
	// **********
	wire			wM_Enable;
	wire			wW_Enable;

	// **********
	// INSTANCE MODULE
	// **********
	assign wM_Enable = (~(|(M_DST_I ^ REG_SRC_I))) & M_DSTR_CS_I & M_VALID_I;
	assign wW_Enable = (~(|(W_DST_I ^ REG_SRC_I))) & W_DSTR_CS_I & W_VALID_I;
	assign REG_BANK_O = ( {8{(~wM_Enable)&(~wW_Enable)}} & REG_BANK_I ) |
						( {8{( wM_Enable)&(M_DSTR_CS_C_I)}} & M_VAL_C_I ) |
						( {8{( wM_Enable)&(M_DSTR_CS_S_I)}} & M_VAL_S_I ) |
						( {8{( wM_Enable)&(M_DSTR_CS_E_I)}} & M_VAL_E_I ) |
						( {8{(~wM_Enable)&( wW_Enable)&(W_DSTR_CS_C_I)}} & W_VAL_C_I ) |
						( {8{(~wM_Enable)&( wW_Enable)&(W_DSTR_CS_S_I)}} & W_VAL_S_I ) |
						( {8{(~wM_Enable)&( wW_Enable)&(W_DSTR_CS_E_I)}} & W_VAL_E_I ) |
						( {8{(~wM_Enable)&( wW_Enable)&(W_DSTR_CS_M_I)}} & W_VAL_M_I );

	// **********
	// MAIN CODE
	// **********

endmodule

MCS8/iverilog-PIPE/cpu.v
// **********
// COPYRIGHT(c) 2018, LUOYIN
// All rights reserved
// 
// IP LIB INDEX	:
// IP Name		: 
// File Name	: 
// Module Name	: 
// Full Name	: 
// 
// Author		: 
// Email		: 
// Data			: 
// Version		: 
//
// Abstract		: 
// Called By	: 
// 
// Modification Histroy
// 
// Description
// F1->F2->F3->D->E->M->W
// **********

// **********
// DEFINE MODEL PORT
// **********
module cpu(
	// Clock
	CLK_I, nRST_I,
	// ICode
	I_DAT_I, I_ADDR_O,
	// DCode
	D_DAT_I, D_DAT_O, D_ADDR_O,
	// IO
	IO_DAT_I, IO_DAT_O, IO_ADDR_O
);

	// **********
	// DEFINE PARAMETER
	// **********

	// **********
	// DEFINE INPUT
	// **********
	// Clock
	input wire CLK_I, nRST_I;
	// ICode
	input wire [7:0] I_DAT_I;
	// DCode
	input wire [7:0] D_DAT_I;
	// IO
	input wire [7:0] IO_DAT_I;

	// **********
	// DEFINE OUTPUT
	// **********
	// ICode
	output wire [13:0] I_ADDR_O;
	// DCode
	output wire [7:0]  D_DAT_O;
	output wire [13:0] D_ADDR_O;
	// IO
	output wire [7:0]  IO_DAT_O;
	output wire [4:0]  IO_ADDR_O;
	
	// **********
	// ATRRIBUTE
	// **********
	// Stage F1
	reg [7:0] rF1_IR;
	reg rF1_IR_valid;
	// Stage F2
	reg [7:0] rF2_IR;
	reg rF2_IR_valid;
	// Stage F3
	reg [7:0] rF3_IR;
	reg rF3_IR_valid;
	// State D
	reg        	rD_valid;
	reg  [7:0] 	rD_icode;
	reg  [3:0] 	rD_ifun;
	reg  [2:0] 	rD_src;
	reg  [2:0] 	rD_dst;
	reg  [7:0] 	rD_valC;				// imm
	reg [13:0] 	rD_valP;
	reg  [1:0] 	rD_count;
	wire		wD_INS_NOP;
	wire [7:0]	wD_forward;
	// ***** Stage E
	reg 		rE_valid;
	reg  [7:0] 	rE_icode;
	reg  [3:0] 	rE_ifun;
	reg  [2:0] 	rE_src;
	reg  [2:0] 	rE_dst;
	reg [13:0] 	rE_valP;
	reg [13:0] 	rE_addrM;
	reg  [4:0] 	rE_addrIO;
	// src
	reg  [7:0] 	rE_valC;				// imm
	reg  [7:0]	rE_valS;				// reg, input B of ALU
	reg  [7:0]	rE_valA;				// input A of ALU
	// control
	wire		wE_dstR_CS;				// ->reg
	wire		wE_dstR_CS_C;			// imm->reg
	wire		wE_dstR_CS_S;			// reg->reg
	wire		wE_dstR_CS_E;			// alu->reg
	wire		wE_dstR_CS_M;			// M->reg
	wire		wE_dstM_CS;				// ->M
	wire		wE_dstM_CS_C;			// imm->M
	wire		wE_dstM_CS_S;			// reg->M
	// ***** Stage M *****
	reg 		rM_valid;
	reg  [7:0] 	rM_icode;
	reg  [2:0] 	rM_dst;
	reg  [7:0] 	rM_valC;				// imm
	reg  [7:0] 	rM_valS;				// reg
	reg  [7:0] 	rM_valE;				// alu
	// control
	reg			rM_dstR_CS;
	reg			rM_dstR_CS_C;			// imm->reg
	reg			rM_dstR_CS_S;			// reg->reg
	reg			rM_dstR_CS_E;			// alu->reg
	reg			rM_dstR_CS_M;			// M->reg
	reg			rM_dstM_CS;				// ->M
	reg			rM_dstM_CS_C;			// imm->M
	reg			rM_dstM_CS_S;			// reg->M
	reg [13:0] 	rM_valP;
	reg [13:0] 	rM_addrM;
	reg  [4:0] 	rM_addrIO;
	// Stage W
	reg 		rW_valid;
	reg  [7:0] 	rW_icode;
	reg  [2:0] 	rW_dst;
	reg  [7:0] 	rW_valC;				// imm
	reg  [7:0] 	rW_valS;				// reg
	reg  [7:0] 	rW_valE;				// alu
	reg  [7:0] 	rW_valM;				// mem
	reg			rW_dstR_CS;				// ->reg
	reg			rW_dstR_CS_C;			// imm->reg
	reg			rW_dstR_CS_S;			// reg->reg
	reg			rW_dstR_CS_E;			// alu->reg
	reg			rW_dstR_CS_M;			// mem->reg
	wire [7:0]	wW_dstVal;
	reg [13:0] 	rW_valP;
	// Stack
	reg [13:0] rStack[7:0];
	reg [2:0] rStack_ndx;
	// RegBank
	reg [7:0] rRegBank[7:0];
	reg [7:0] rTest;
	
	wire wDoubleByte;
	wire wTripleByte;
	
	wire wINS_NOP;
	
	// **********
	// INSTANCE MODULE
	// **********
	assign I_ADDR_O = rStack[rStack_ndx];
	assign wDoubleByte = (~rF3_IR[7])&(~rF3_IR[6])&( rF3_IR[2])&(~rF3_IR[0]);
	assign wTripleByte = (~rF3_IR[7])&( rF3_IR[6])&(~rF3_IR[0]);
	assign wSingle = (~wDoubleByte) & (~wTripleByte);
	assign wINS_NOP = (~rF3_IR[7])&(~rF3_IR[6])&(~rF3_IR[5])&(~rF3_IR[4])&(~rF3_IR[3])&(~rF3_IR[2])&(~rF3_IR[1]);
	
	// **** Stage D ****
	// NOP
	assign wD_INS_NOP = ~(|rD_icode[7:1]); 
	
	// **** Stage E ****
	// src select
	// LrI: 00DDD110
	assign wE_dstR_CS_C = (~rE_icode[7])&(~rE_icode[6])&(~(&rE_icode[5:3]))&( rE_icode[2])&( rE_icode[1])&(~rE_icode[0]);	// LrI
	// Lrr: 11DDDSSS
	assign wE_dstR_CS_S = ( rE_icode[7])&( rE_icode[6])&(~(&rE_icode[5:3]))&(~(&rE_icode[2:0]));							// Lrr
	// LrM: 11DDD111
	assign wE_dstR_CS_M = ( rE_icode[7])&( rE_icode[6])&(~(&rE_icode[5:3]))&(&rE_icode[2:0]);								// Lrr
	// INr/DCr/ALUr/ALUI/ROT
	// INr/DCr: 00DDD00x
	assign wE_dstR_CS_E = ( (~rE_icode[7]) & (~rE_icode[6]) & (~(&rE_icode[5:3])) & (~(|rE_icode[5:3])) & (~rE_icode[2]) & (~rE_icode[1]) ) |		// INr/DCr: 00DDD00x
						  ( ( rE_icode[7]) & (~rE_icode[6]) & (~(&rE_icode[2:0])) ) | 																// ALUr: 10PPPSSS
						  ( (~rE_icode[7]) & (~rE_icode[6]) & ( rE_icode[2]) & (~rE_icode[1]) & (~rE_icode[0]) ) |									// ALUI: 00PPP100
						  ( (~rE_icode[7]) & (~rE_icode[6]) & (~rE_icode[5]) & (~rE_icode[2]) & ( rE_icode[1]) & (~rE_icode[0]) );					// ROT:  000RR010
	// dst control
	assign wE_dstR_CS = wE_dstR_CS_C | wE_dstR_CS_S | wE_dstR_CS_M | wE_dstR_CS_E;
	cpu_forward uForward(
		.REG_BANK_I(rRegBank[rD_src]), .REG_SRC_I(rD_src),
		.M_VAL_C_I(rM_valC), .M_VAL_S_I(rM_valS), .M_VAL_E_I(rM_valE),
		.W_VAL_C_I(rW_valC), .W_VAL_S_I(rW_valS), .W_VAL_E_I(rW_valE), .W_VAL_M_I(rW_valM),
		.M_DST_I(rM_dst), .M_VALID_I(rM_valid), .M_DSTR_CS_I(rM_dstR_CS), .M_DSTR_CS_C_I(rM_dstR_CS_C), .M_DSTR_CS_S_I(rM_dstR_CS_S), .M_DSTR_CS_E_I(rM_dstR_CS_E),
		.W_DST_I(rW_dst), .W_VALID_I(rW_valid), .W_DSTR_CS_I(rW_dstR_CS), .W_DSTR_CS_C_I(rW_dstR_CS_C), .W_DSTR_CS_S_I(rW_dstR_CS_S), .W_DSTR_CS_E_I(rW_dstR_CS_E), .W_DSTR_CS_M_I(rW_dstR_CS_M),
		.REG_BANK_O(wD_forward)
	);
	
	// LMI
	assign wE_dstM_CS_C = (~rE_icode[7])&(~rE_icode[6])&(&rE_icode[5:3])&( rE_icode[2])&( rE_icode[1])&(~rE_icode[0]);		// LMI
	// LMr
	assign wE_dstM_CS_S = ( rE_icode[7])&( rE_icode[6])&(&rE_icode[5:3])&(~(&rE_icode[2:0]));								// LMr
	// dst control
	assign wE_dstM_CS = wE_dstM_CS_C | wE_dstM_CS_S;
	
	// **** Stage W ****
	// src select
	
	// dstVal
	assign wW_dstVal = ( {8{rW_dstR_CS_C}} & rW_valC ) |
					( {8{rW_dstR_CS_S}} & rW_valS ) |
					( {8{rW_dstR_CS_M}} & rW_valM ) |
					( {8{rW_dstR_CS_E}} & rW_valE );
	
	// **********
	// MAIN CODE
	// **********
	// Stack Control
	always @(posedge CLK_I) begin
		if(~nRST_I) begin
			rStack[0] <= 14'b0;
			rStack[1] <= 14'b0;
			rStack[2] <= 14'b0;
			rStack[3] <= 14'b0;
			rStack[4] <= 14'b0;
			rStack[5] <= 14'b0;
			rStack[6] <= 14'b0;
			rStack[7] <= 14'b0;
			rStack_ndx <= 3'b0;
			end
		else begin
			rStack[rStack_ndx] <= rStack[rStack_ndx]+1;
			end
		end
		
	// Fetch 2 (F1->F2)
	always @(posedge CLK_I) begin
		if(~nRST_I) begin
			rF2_IR <= 8'b0;
			rF2_IR_valid <= 1'b0;
			end
		else begin
			rF2_IR <= rF1_IR;
			rF2_IR_valid <= rF1_IR_valid;
			end
		end
		
	// Fetch 3 (F2->F3)
	always @(posedge CLK_I) begin
		if(~nRST_I) begin
			rF3_IR <= 8'b0;
			rF3_IR_valid <= 8'b0;
			end
		else begin
			rF3_IR <= rF2_IR;
			rF3_IR_valid <= rF2_IR_valid;
			end
		end
		
	// Fetch (F3->D)
	always @(posedge CLK_I) begin
		if(~nRST_I) begin
			rD_valid <= 1'b0;
			rD_icode <= 8'b0;
			rD_ifun  <= 4'b0;
			rD_src   <= 3'b0;
			rD_dst   <= 3'b0;
			rD_valC  <= 8'b0;
			rD_valP  <= 14'b0;
			rD_count <= 2'b0;
			end
		else begin
			if((~rD_count[1])&(~rD_count[0])) begin
				rD_icode <= rF3_IR;
				rD_ifun  <= { (~rF3_IR[2])&( rF3_IR[1])&(~rF3_IR[0]), rF3_IR[5], rF3_IR[4], rF3_IR[3] };
				rD_src   <= rF3_IR[2:0];
				rD_dst   <= rF3_IR[5:3];
				rD_valC  <= rF2_IR;
				rD_valP  <= { rF1_IR[5:0], rF2_IR };
				rD_valid <= rF3_IR_valid & (~wINS_NOP);
				if(wDoubleByte)
					rD_count <= 1;
				else if(wTripleByte)
					rD_count <= 2;
				else
					rD_count <= 0;
				end
			else begin
				rD_count <= rD_count-1;
				rD_valid <= 1'b0;
				end
			end
		end
	
	// Decode (D->E)
	always @(posedge CLK_I) begin
		if(~nRST_I) begin
			rE_valid 		<= 1'b0;
			rE_icode 		<= 8'b0;
			rE_ifun  		<= 4'b0;
			rE_dst	 		<= 3'b0;
			rE_valP  		<= 14'b0;
			rE_valC  		<= 8'b0;
			end
		else begin
			rE_valid <= rD_valid;
			
			if(rD_valid) begin
				rE_icode 	<= rD_icode;
				rE_ifun  	<= rD_ifun;
				rE_src		<= rD_src;
				rE_dst  	<= rD_dst;
				rE_valP  	<= rD_valP;
				
				// valC
				rE_valC  <= rD_valC;
				
				// valA
				casex(rD_icode)
					8'b00xxx00x: begin			// INr, DCr
						if(~wD_INS_NOP)
							rE_valA <= rRegBank[rD_dst];
						end
					8'b000xx010: begin			// ROT
						rE_valA <= rRegBank[3'b000];
						end
					8'b00xxx100: begin			// ALUI
						rE_valA <= rRegBank[3'b000];
						end
					8'b10xxxxxx: begin			// ALUr
						rE_valA <= rRegBank[rD_src];
						end
					endcase
				
				// valS
				casex(rD_icode)
					8'b00xxx000: begin
						rE_valS <= 8'b00000001;
						end
					8'b00xxx001: begin
						rE_valS <= 8'b11111111;
						end
					8'b00xxx100: begin
						rE_valS <= rD_valC;
						end
					8'b00xxx110: begin
						rE_valS <= rD_valC;
						end
					8'b11xxxxxx: begin
						rE_valS <= rRegBank[rD_src];
						end
					default: begin
						rE_valS <= 8'b0;
						end
					endcase
				end
				
				// src select
				
			end
		end
		
	// Execute (E->M)
	always @(posedge CLK_I) begin
		if(~nRST_I) begin
			rM_valid 		<= 1'b0;
			rM_icode 		<= 8'b0;
			// src
			rM_valC			<= 8'b0;
			rM_valS			<= 8'b0;
			rM_valE			<= 8'b0;
			rM_dst			<= 8'b0;
			end
		else begin
			rM_valid		<= rE_valid;
			if(rE_valid) begin
				rM_icode	<= rE_icode;
				rM_valC		<= rE_valC;
				rM_dst		<= rE_dst;
				// src/dst control
				rM_dstR_CS		<= wE_dstR_CS;
				rM_dstR_CS_C	<= wE_dstR_CS_C;
				rM_dstR_CS_S	<= wE_dstR_CS_S;
				rM_dstR_CS_E	<= wE_dstR_CS_E;
				rM_dstR_CS_M	<= wE_dstR_CS_M;
				rM_dstM_CS		<= wE_dstM_CS;
				rM_dstM_CS_C	<= wE_dstM_CS_C;
				rM_dstM_CS_S	<= wE_dstM_CS_S;
				end
			end
		end
		
	// Memory (M->W)
	always @(posedge CLK_I) begin
		if(~nRST_I) begin
			rW_valid		<= 1'b0;
			rW_icode		<= 8'b0;
			// src
			rW_valC			<= 8'b0;
			rW_valS			<= 8'b0;
			rW_valE			<= 8'b0;
			rW_valM			<= 8'b0;
			rW_dst			<= 8'b0;
			end
		else begin
			rW_valid		<= rM_valid;
			if(rM_valid) begin
				rW_icode	<= rM_icode;
				rW_valC		<= rM_valC;
				rW_dst		<= rM_dst;
				// src/dst control
				rW_dstR_CS		<= rM_dstR_CS;
				rW_dstR_CS_C	<= rM_dstR_CS_C;
				rW_dstR_CS_S	<= rM_dstR_CS_S;
				rW_dstR_CS_E	<= rM_dstR_CS_E;
				rW_dstR_CS_M	<= rM_dstR_CS_M;
				end
			end
		end
	
	// WriteBack (ROM->F1)
	always @(posedge CLK_I) begin
		if(~nRST_I) begin
			rRegBank[0] <= 8'b0;
			rRegBank[1] <= 8'b0;
			rRegBank[2] <= 8'b0;
			rRegBank[3] <= 8'b0;
			rRegBank[4] <= 8'b0;
			rRegBank[5] <= 8'b0;
			rRegBank[6] <= 8'b0;
			rRegBank[7] <= 8'b0;
			rF1_IR <= 8'b0;
			rF1_IR_valid <=1'b0;
			end
		else begin
			rF1_IR <= I_DAT_I;
			rF1_IR_valid <= 1'b1;
			if(rW_valid) begin
				if(rW_dstR_CS) begin
					rRegBank[rW_dst] <= wW_dstVal;
					rTest <= wW_dstVal;
					end
				end
			end
		end
	
endmodule

MCS8/iverilog-PIPE/bench_clock.v
// **********
// COPYRIGHT(c) 2018, LUOYIN
// All rights reserved
// 
// IP LIB INDEX	:
// IP Name		: 
// File Name	: 
// Module Name	: 
// Full Name	: 
// 
// Author		: 
// Email		: 
// Data			: 
// Version		: 
//
// Abstract		: 
// Called By	: 
// 
// Modification Histroy
// 
// **********

// **********
// DEFINE MODEL PORT
// **********
//
module bench_clock(
	CLK_O,
	nRST_O
);

	// **********
	// DEFINE PARAMETER
	// **********

	// **********
	// DEFINE INPUT
	// **********

	// **********
	// DEFINE OUTPUT
	// **********
	output reg CLK_O;
	output reg nRST_O;
	
	// **********
	// ATRRIBUTE
	// **********

	// **********
	// INSTANCE MODULE
	// **********

	// **********
	// MAIN CODE
	// **********
	initial begin
		CLK_O=1'b0;
		nRST_O=1'b1;
		forever #5 CLK_O=~CLK_O;
		end
		
	initial begin
		#100 nRST_O=1'b0;
		#100 nRST_O=1'b1;
		end
	
	initial begin
		#600 $finish;
		end
	
endmodule

MCS8/iverilog-PIPE/bench_top.v
// **********
// COPYRIGHT(c) 2018, LUOYIN
// All rights reserved
// 
// IP LIB INDEX	:
// IP Name		: 
// File Name	: 
// Module Name	: 
// Full Name	: 
// 
// Author		: 
// Email		: 
// Data			: 
// Version		: 
//
// Abstract		: 
// Called By	: 
// 
// Modification Histroy
// 
// **********

// **********
// DEFINE MODEL PORT
// **********
//
module bench_top();

	// **********
	// DEFINE PARAMETER
	// **********

	// **********
	// DEFINE INPUT
	// **********

	// **********
	// DEFINE OUTPUT
	// **********

	// **********
	// ATRRIBUTE
	// **********
	wire wCLK, wnRST;
	// ICODE
	wire [13:0] wI_ADDR;
	wire [7:0] wI_DAT;

	// **********
	// INSTANCE MODULE
	// **********
	bench_clock uClock(
		.CLK_O(wCLK), .nRST_O(wnRST)
	);
	cpu uCPU(
		.CLK_I(wCLK), .nRST_I(wnRST),
		.I_DAT_I(wI_DAT), .I_ADDR_O(wI_ADDR)
	);
	rom uRom(
		.ADDR_I(wI_ADDR),
		.DAT_O(wI_DAT)
	);

	// **********
	// MAIN CODE
	// **********
	initial begin
		$dumpvars(0, uClock);
		$dumpvars(0, uCPU);
		$dumpvars(0, uRom);
		end
	
endmodule

MCS8/iverilog-PIPE/dump.vcd
$date
	Fri Apr 20 17:00:00 2018
$end
$version
	Icarus Verilog
$end
$timescale
	1s
$end
$scope module bench_top $end
$scope module uClock $end
$var reg 1 ! CLK_O $end
$var reg 1 " nRST_O $end
$upscope $end
$upscope $end
$scope module bench_top $end
$scope module uCPU $end
$var wire 1 # CLK_I $end
$var wire 14 $ D_ADDR_O [13:0] $end
$var wire 8 % D_DAT_I [7:0] $end
$var wire 8 & D_DAT_O [7:0] $end
$var wire 5 ' IO_ADDR_O [4:0] $end
$var wire 8 ( IO_DAT_I [7:0] $end
$var wire 8 ) IO_DAT_O [7:0] $end
$var wire 14 * I_ADDR_O [13:0] $end
$var wire 8 + I_DAT_I [7:0] $end
$var wire 1 , nRST_I $end
$var wire 1 - wD_INS_NOP $end
$var wire 8 . wD_forward [7:0] $end
$var wire 1 / wDoubleByte $end
$var wire 1 0 wE_dstM_CS $end
$var wire 1 1 wE_dstM_CS_C $end
$var wire 1 2 wE_dstM_CS_S $end
$var wire 1 3 wE_dstR_CS $end
$var wire 1 4 wE_dstR_CS_C $end
$var wire 1 5 wE_dstR_CS_E $end
$var wire 1 6 wE_dstR_CS_M $end
$var wire 1 7 wE_dstR_CS_S $end
$var wire 1 8 wINS_NOP $end
$var wire 1 9 wSingle $end
$var wire 1 : wTripleByte $end
$var wire 8 ; wW_dstVal [7:0] $end
$var reg 2 < rD_count [1:0] $end
$var reg 3 = rD_dst [2:0] $end
$var reg 8 > rD_icode [7:0] $end
$var reg 4 ? rD_ifun [3:0] $end
$var reg 3 @ rD_src [2:0] $end
$var reg 8 A rD_valC [7:0] $end
$var reg 14 B rD_valP [13:0] $end
$var reg 1 C rD_valid $end
$var reg 3 D rE_dst [2:0] $end
$var reg 8 E rE_icode [7:0] $end
$var reg 4 F rE_ifun [3:0] $end
$var reg 3 G rE_src [2:0] $end
$var reg 8 H rE_valA [7:0] $end
$var reg 8 I rE_valC [7:0] $end
$var reg 14 J rE_valP [13:0] $end
$var reg 8 K rE_valS [7:0] $end
$var reg 1 L rE_valid $end
$var reg 8 M rF1_IR [7:0] $end
$var reg 1 N rF1_IR_valid $end
$var reg 8 O rF2_IR [7:0] $end
$var reg 1 P rF2_IR_valid $end
$var reg 8 Q rF3_IR [7:0] $end
$var reg 1 R rF3_IR_valid $end
$var reg 3 S rM_dst [2:0] $end
$var reg 1 T rM_dstM_CS $end
$var reg 1 U rM_dstM_CS_C $end
$var reg 1 V rM_dstM_CS_S $end
$var reg 1 W rM_dstR_CS $end
$var reg 1 X rM_dstR_CS_C $end
$var reg 1 Y rM_dstR_CS_E $end
$var reg 1 Z rM_dstR_CS_M $end
$var reg 1 [ rM_dstR_CS_S $end
$var reg 8 \ rM_icode [7:0] $end
$var reg 8 ] rM_valC [7:0] $end
$var reg 8 ^ rM_valE [7:0] $end
$var reg 8 _ rM_valS [7:0] $end
$var reg 1 ` rM_valid $end
$var reg 3 a rStack_ndx [2:0] $end
$var reg 8 b rTest [7:0] $end
$var reg 3 c rW_dst [2:0] $end
$var reg 1 d rW_dstR_CS $end
$var reg 1 e rW_dstR_CS_C $end
$var reg 1 f rW_dstR_CS_E $end
$var reg 1 g rW_dstR_CS_M $end
$var reg 1 h rW_dstR_CS_S $end
$var reg 8 i rW_icode [7:0] $end
$var reg 8 j rW_valC [7:0] $end
$var reg 8 k rW_valE [7:0] $end
$var reg 8 l rW_valM [7:0] $end
$var reg 8 m rW_valS [7:0] $end
$var reg 1 n rW_valid $end
$scope module uForward $end
$var wire 1 o M_DSTR_CS_C_I $end
$var wire 1 p M_DSTR_CS_E_I $end
$var wire 1 q M_DSTR_CS_I $end
$var wire 1 r M_DSTR_CS_S_I $end
$var wire 3 s M_DST_I [2:0] $end
$var wire 1 t M_VALID_I $end
$var wire 8 u M_VAL_C_I [7:0] $end
$var wire 8 v M_VAL_E_I [7:0] $end
$var wire 8 w M_VAL_S_I [7:0] $end
$var wire 8 x REG_BANK_I [7:0] $end
$var wire 8 y REG_BANK_O [7:0] $end
$var wire 3 z REG_SRC_I [2:0] $end
$var wire 1 { W_DSTR_CS_C_I $end
$var wire 1 | W_DSTR_CS_E_I $end
$var wire 1 } W_DSTR_CS_I $end
$var wire 1 ~ W_DSTR_CS_M_I $end
$var wire 1 !" W_DSTR_CS_S_I $end
$var wire 3 "" W_DST_I [2:0] $end
$var wire 1 #" W_VALID_I $end
$var wire 8 $" W_VAL_C_I [7:0] $end
$var wire 8 %" W_VAL_E_I [7:0] $end
$var wire 8 &" W_VAL_M_I [7:0] $end
$var wire 8 '" W_VAL_S_I [7:0] $end
$var wire 1 (" wM_Enable $end
$var wire 1 )" wW_Enable $end
$upscope $end
$upscope $end
$upscope $end
$scope module bench_top $end
$scope module uRom $end
$var wire 14 *" ADDR_I [13:0] $end
$var reg 8 +" DAT_O [7:0] $end
$upscope $end
$upscope $end
$enddefinitions $end
#0
$dumpvars
bx +"
bx *"
x)"
x("
bx '"
bx &"
bx %"
bx $"
x#"
bx ""
x!"
x~
x}
x|
x{
bx z
bx y
bx x
bx w
bx v
bx u
xt
bx s
xr
xq
xp
xo
xn
bx m
bx l
bx k
bx j
bx i
xh
xg
xf
xe
xd
bx c
bx b
bx a
x`
bx _
bx ^
bx ]
bx \
x[
xZ
xY
xX
xW
xV
xU
xT
bx S
xR
bx Q
xP
bx O
xN
bx M
xL
bx K
bx J
bx I
bx H
bx G
bx F
bx E
bx D
xC
bx B
bx A
bx @
bx ?
bx >
bx =
bx <
bx ;
x:
x9
x8
x7
x6
x5
x4
x3
x2
x1
x0
x/
bx .
x-
1,
bx +
bx *
bz )
bz (
bz '
bz &
bz %
bz $
0#
1"
0!
$end
#5
0C
1N
1!
1#
#10
0!
0#
#15
0L
1P
1!
1#
#20
0!
0#
#25
0("
1R
0`
0t
1!
1#
#30
0!
0#
#35
0)"
0n
0#"
1!
1#
#40
0!
0#
#45
1!
1#
#50
0!
0#
#55
1!
1#
#60
0!
0#
#65
1!
1#
#70
0!
0#
#75
1!
1#
#80
0!
0#
#85
1!
1#
#90
0!
0#
#95
1!
1#
#100
0!
0#
0"
0,
#105
b1110 +"
b1110 +
13
15
18
b0 .
b0 y
19
07
00
0/
0:
04
01
02
b0 ;
1-
06
b0 a
b0 *
b0 *"
0P
b0 O
0R
b0 Q
b0 <
b0 B
b0 A
b0 =
b0 @
b0 x
b0 z
b0 ?
b0 >
b0 I
b0 J
b0 D
b0 F
b0 E
b0 S
b0 s
b0 ^
b0 v
b0 _
b0 w
b0 ]
b0 u
b0 \
b0 c
b0 ""
b0 l
b0 &"
b0 k
b0 %"
b0 m
b0 '"
b0 j
b0 $"
b0 i
0N
b0 M
1!
1#
#110
0!
0#
#115
1!
1#
#120
0!
0#
#125
1!
1#
#130
0!
0#
#135
1!
1#
#140
0!
0#
#145
1!
1#
#150
0!
0#
#155
1!
1#
#160
0!
0#
#165
1!
1#
#170
0!
0#
#175
1!
1#
#180
0!
0#
#185
1!
1#
#190
0!
0#
#195
1!
1#
#200
0!
0#
1"
1,
#205
b10101010 +"
b10101010 +
b1 *
b1 *"
1N
b1110 M
1!
1#
#210
0!
0#
#215
b10110 +"
b10110 +
b10101010 M
b111000000000 B
1P
b1110 O
b10 *
b10 *"
1!
1#
#220
0!
0#
#225
b1010101 +"
b1010101 +
09
1/
08
b11 *
b11 *"
b10101010 O
1R
b1110 Q
b10101000001110 B
b1110 A
b10110 M
1!
1#
#230
0!
0#
#235
b11000001 +"
b11000001 +
19
0/
0-
b1010101 M
b1 <
1C
b1011010101010 B
b10101010 A
b1 =
b110 @
b110 z
b1 ?
b1110 >
b10101010 Q
b10110 O
b100 *
b100 *"
1!
1#
#240
0!
0#
#245
b10000010 +"
b10000010 +
09
05
1/
14
b101 *
b101 *"
b1010101 O
b10110 Q
0C
b0 <
b10101010 K
b10101010 I
b1011010101010 J
b1 D
b110 G
b1 F
b1110 E
1L
b11000001 M
1!
1#
#250
0!
0#
#255
b11111111 +"
b11111111 +
19
0/
b10000010 M
0V
0U
0T
0Z
0Y
0p
0[
0r
1X
1o
1W
1q
b1 S
b1 s
b10101010 ]
b10101010 u
b1110 \
1`
1t
0L
b1 <
1C
b101010101 B
b1010101 A
b10 =
b10 ?
b10110 >
b1010101 Q
b11000001 O
b110 *
b110 *"
1!
1#
#260
0!
0#
#265
bx +"
bx +
b10101010 ;
b111 *
b111 *"
b10000010 O
b11000001 Q
0C
b0 <
b1010101 K
b1010101 I
b101010101 J
b10 D
b10 F
b10110 E
1L
0`
0t
0g
0~
0f
0|
0h
0!"
1e
1{
1d
1}
b1 c
b1 ""
b10101010 j
b10101010 $"
b1110 i
1n
1#"
b11111111 M
1!
1#
#270
0!
0#
#275
b10101010 .
b10101010 y
b10101010 b
b10101010 x
bx M
0n
0#"
b10 S
b10 s
b1010101 ]
b1010101 u
b10110 \
1`
1t
0L
1C
b11111110000010 B
b10000010 A
b0 =
b1 @
b1 z
b0 ?
b11000001 >
b10000010 Q
b11111111 O
b1000 *
b1000 *"
1!
1#
#280
0!
0#
