MCS8/iverilog-PIPE/rom.v
// **********
// COPYRIGHT(c) 2018, LUOYIN
// All rights reserved
// 
// IP LIB INDEX	: 
// IP Name		: BASIC
// File Name	: rom.v
// Module Name	: rom
// Full Name	: ROM
// 
// Author		: LUO YIN
// Email		: luoyin1986@gmail.com
// Data			: 2018/04/09
// Version		: 1.0
//
// Abstract		:
// Called By	: 
// 
// Modification Histroy
// 
// **********

// **********
// DEFINE MODEL PORT
// **********
//
module rom(
	ADDR_I,
	DAT_O
);

	// **********
	// DEFINE PARAMETER
	// **********

	// **********
	// DEFINE INPUT
	// **********
	input wire [13:0] ADDR_I;

	// **********
	// DEFINE OUTPUT
	// **********
	output reg [7:0] DAT_O;

	// **********
	// ATRRIBUTE
	// **********
	reg [7:0] mem[0:16383];

	// **********
	// INSTANCE MODULE
	// **********

	// **********
	// MAIN CODE
	// **********
	initial begin
		// $readmemh("rom.dat", mem);
		$readmemb("test1.bin", mem);
		end
	
	always @(ADDR_I) begin
		DAT_O <= mem[ADDR_I];
		end

endmodule

MCS8/iverilog-PIPE/cpu.v
// **********
// COPYRIGHT(c) 2018, LUOYIN
// All rights reserved
// 
// IP LIB INDEX	:
// IP Name		: 
// File Name	: 
// Module Name	: 
// Full Name	: 
// 
// Author		: 
// Email		: 
// Data			: 
// Version		: 
//
// Abstract		: 
// Called By	: 
// 
// Modification Histroy
// 
// Description
// F1->F2->F3->D->E->M->W
// **********

// **********
// DEFINE MODEL PORT
// **********
module cpu(
	// Clock
	CLK_I, nRST_I,
	// ICode
	I_DAT_I, I_ADDR_O,
	// DCode
	D_DAT_I, D_DAT_O, D_ADDR_O,
	// IO
	IO_DAT_I, IO_DAT_O, IO_ADDR_O
);

	// **********
	// DEFINE PARAMETER
	// **********

	// **********
	// DEFINE INPUT
	// **********
	// Clock
	input wire CLK_I, nRST_I;
	// ICode
	input wire [7:0] I_DAT_I;
	// DCode
	input wire [7:0] D_DAT_I;
	// IO
	input wire [7:0] IO_DAT_I;

	// **********
	// DEFINE OUTPUT
	// **********
	// ICode
	output wire [13:0] I_ADDR_O;
	// DCode
	output wire [7:0]  D_DAT_O;
	output wire [13:0] D_ADDR_O;
	// IO
	output wire [7:0]  IO_DAT_O;
	output wire [4:0]  IO_ADDR_O;
	
	// **********
	// ATRRIBUTE
	// **********
	// Stage F1
	reg [7:0] rF1_IR;
	reg rF1_IR_valid;
	// Stage F2
	reg [7:0] rF2_IR;
	reg rF2_IR_valid;
	// Stage F3
	reg [7:0] rF3_IR;
	reg rF3_IR_valid;
	// State D
	reg        	rD_valid;
	reg  [4:0] 	rD_icode;
	reg  [3:0] 	rD_ifun;
	reg  [2:0] 	rD_srcR;
	reg  [2:0] 	rD_dstR;
	reg  [7:0] 	rD_valC;
	reg [13:0] 	rD_valP;
	reg  [1:0] 	rD_count;
	// Stage E
	reg rE_valid;
	reg  [4:0] 	rE_icode;
	reg  [3:0] 	rE_ifun;
	reg  [2:0] 	rE_dstR;
	reg  [7:0]	rE_valA;
	reg  [7:0]	rE_valS;
	reg  [7:0] 	rE_valC;
	reg [13:0] 	rE_valP;
	reg  [7:0] 	rE_valH;
	reg  [7:0] 	rE_valL;
	// Stage M
	reg rM_valid;
	reg  [4:0] rM_icode;
	reg  [2:0] rM_dstR;
	reg  [7:0] rM_valE;
	// Stage W
	
	// Stack
	reg [13:0] rStack[7:0];
	reg [2:0] rStack_ndx;
	// RegBank
	reg [7:0] rRegBank[7:0];
	
	wire wDoubleByte;
	wire wTripleByte;
	
	// **********
	// INSTANCE MODULE
	// **********
	assign I_ADDR_O = rStack[rStack_ndx];
	assign wDoubleByte = (~rF3_IR[7])&(~rF3_IR[6])&( rF3_IR[2])&(~rF3_IR[0]);
	assign wTripleByte = (~rF3_IR[7])&( rF3_IR[6])&(~rF3_IR[0]);
	assign wSingle = (~wDoubleByte) & (~wTripleByte);
	
	// **********
	// MAIN CODE
	// **********
	// Stack Control
	always @(posedge CLK_I) begin
		if(~nRST_I) begin
			rStack[0] <= 14'b0;
			rStack[1] <= 14'b0;
			rStack[2] <= 14'b0;
			rStack[3] <= 14'b0;
			rStack[4] <= 14'b0;
			rStack[5] <= 14'b0;
			rStack[6] <= 14'b0;
			rStack[7] <= 14'b0;
			rStack_ndx <= 3'b0;
			end
		else begin
			rStack[rStack_ndx] <= rStack[rStack_ndx]+1;
			end
		end
		
	// Fetch 2 (F1->F2)
	always @(posedge CLK_I) begin
		if(~nRST_I) begin
			rF2_IR <= 8'b0;
			rF2_IR_valid <= 1'b0;
			end
		else begin
			rF2_IR <= rF1_IR;
			rF2_IR_valid <= rF1_IR_valid;
			end
		end
		
	// Fetch 3 (F2->F3)
	always @(posedge CLK_I) begin
		if(~nRST_I) begin
			rF3_IR <= 8'b0;
			rF3_IR_valid <= 8'b0;
			end
		else begin
			rF3_IR <= rF2_IR;
			rF3_IR_valid <= rF2_IR_valid;
			end
		end
		
	// Fetch (F3->D)
	always @(posedge CLK_I) begin
		if(~nRST_I) begin
			rD_valid <= 1'b0;
			rD_icode <= 5'b0;
			rD_ifun  <= 4'b0;
			rD_dstR  <= 3'b0;
			rD_srcR  <= 3'b0;
			rD_valC  <= 8'b0;
			rD_valP  <= 14'b0;
			rD_count <= 2'b0;
			end
		else begin
			if((~rD_count[1])&(~rD_count[0])) begin
				rD_icode <= { rF3_IR[7], rF3_IR[6], rF3_IR[2], rF3_IR[1], rF3_IR[0] };
				rD_ifun  <= { (~rF3_IR[2])&( rF3_IR[1])&(~rF3_IR[0]), rF3_IR[5], rF3_IR[4], rF3_IR[3] };
				rD_srcR  <= rF3_IR[2:0];
				rD_dstR  <= rF3_IR[5:3];
				rD_valC  <= rF2_IR;
				rD_valP  <= { rF1_IR[5:0], rF2_IR };
				rD_valid <= rF3_IR_valid;
				if(wDoubleByte)
					rD_count <= 1;
				else if(wTripleByte)
					rD_count <= 2;
				else
					rD_count <= 0;
				end
			else begin
				rD_count <= rD_count-1;
				rD_valid <= 1'b0;
				end
			end
		end
	
	// Decode (D->E)
	always @(posedge CLK_I) begin
		if(~nRST_I) begin
			rE_valid <= 1'b0;
			rE_icode <= 5'b0;
			rE_ifun  <= 4'b0;
			rE_dstR  <= 3'b0;
			rE_valC  <= 8'b0;
			rE_valP  <= 14'b0;
			end
		else begin
			rE_valid <= rD_valid;
			rE_icode <= rD_icode;
			rE_ifun  <= rD_ifun;
			rE_dstR  <= rD_dstR;
			rE_valC  <= rD_valC;
			rE_valP  <= rD_valP;
			
			// valA
			
			// valS
			casex(rD_icode)
				5'b00110: begin
					rE_valS <= rD_valC;
					end
				default: begin
					rE_valS <= 8'b0;
					end
				endcase
			end
		end
		
	// Execute (E->M)
	always @(posedge CLK_I) begin
		if(~nRST_I) begin
			rM_icode <= 5'b0;
			
			end
		else begin
			
			end
		end
		
	// Memory (M->W)
	
	// WriteBack (ROM->F1)
	always @(posedge CLK_I) begin
		if(~nRST_I) begin
			rRegBank[0] <= 8'b0;
			rRegBank[1] <= 8'b0;
			rRegBank[2] <= 8'b0;
			rRegBank[3] <= 8'b0;
			rRegBank[4] <= 8'b0;
			rRegBank[5] <= 8'b0;
			rRegBank[6] <= 8'b0;
			rRegBank[7] <= 8'b0;
			rF1_IR <= 8'b0;
			rF1_IR_valid <=1'b0;
			end
		else begin
			rF1_IR <= I_DAT_I;
			rF1_IR_valid <= 1'b1;
			end
		end
	
endmodule

MCS8/iverilog-PIPE/bench_clock.v
// **********
// COPYRIGHT(c) 2018, LUOYIN
// All rights reserved
// 
// IP LIB INDEX	:
// IP Name		: 
// File Name	: 
// Module Name	: 
// Full Name	: 
// 
// Author		: 
// Email		: 
// Data			: 
// Version		: 
//
// Abstract		: 
// Called By	: 
// 
// Modification Histroy
// 
// **********

// **********
// DEFINE MODEL PORT
// **********
//
module bench_clock(
	CLK_O,
	nRST_O
);

	// **********
	// DEFINE PARAMETER
	// **********

	// **********
	// DEFINE INPUT
	// **********

	// **********
	// DEFINE OUTPUT
	// **********
	output reg CLK_O;
	output reg nRST_O;
	
	// **********
	// ATRRIBUTE
	// **********

	// **********
	// INSTANCE MODULE
	// **********

	// **********
	// MAIN CODE
	// **********
	initial begin
		CLK_O=1'b0;
		nRST_O=1'b1;
		forever #5 CLK_O=~CLK_O;
		end
		
	initial begin
		#100 nRST_O=1'b0;
		#100 nRST_O=1'b1;
		end
	
	initial begin
		#600 $finish;
		end
	
endmodule

MCS8/iverilog-PIPE/bench_top.v
// **********
// COPYRIGHT(c) 2018, LUOYIN
// All rights reserved
// 
// IP LIB INDEX	:
// IP Name		: 
// File Name	: 
// Module Name	: 
// Full Name	: 
// 
// Author		: 
// Email		: 
// Data			: 
// Version		: 
//
// Abstract		: 
// Called By	: 
// 
// Modification Histroy
// 
// **********

// **********
// DEFINE MODEL PORT
// **********
//
module bench_top();

	// **********
	// DEFINE PARAMETER
	// **********

	// **********
	// DEFINE INPUT
	// **********

	// **********
	// DEFINE OUTPUT
	// **********

	// **********
	// ATRRIBUTE
	// **********
	wire wCLK, wnRST;
	// ICODE
	wire [13:0] wI_ADDR;
	wire [7:0] wI_DAT;

	// **********
	// INSTANCE MODULE
	// **********
	bench_clock uClock(
		.CLK_O(wCLK), .nRST_O(wnRST)
	);
	cpu uCPU(
		.CLK_I(wCLK), .nRST_I(wnRST),
		.I_DAT_I(wI_DAT), .I_ADDR_O(wI_ADDR)
	);
	rom uRom(
		.ADDR_I(wI_ADDR),
		.DAT_O(wI_DAT)
	);

	// **********
	// MAIN CODE
	// **********
	initial begin
		$dumpvars(0, uClock);
		$dumpvars(0, uCPU);
		$dumpvars(0, uRom);
		end
	
endmodule

MCS8/iverilog-PIPE/dump.vcd
$date
	Wed Apr 18 16:53:15 2018
$end
$version
	Icarus Verilog
$end
$timescale
	1s
$end
$scope module bench_top $end
$scope module uClock $end
$var reg 1 ! CLK_O $end
$var reg 1 " nRST_O $end
$upscope $end
$upscope $end
$scope module bench_top $end
$scope module uCPU $end
$var wire 1 # CLK_I $end
$var wire 14 $ D_ADDR_O [13:0] $end
$var wire 8 % D_DAT_I [7:0] $end
$var wire 8 & D_DAT_O [7:0] $end
$var wire 5 ' IO_ADDR_O [4:0] $end
$var wire 8 ( IO_DAT_I [7:0] $end
$var wire 8 ) IO_DAT_O [7:0] $end
$var wire 14 * I_ADDR_O [13:0] $end
$var wire 8 + I_DAT_I [7:0] $end
$var wire 1 , nRST_I $end
$var wire 1 - wDoubleByte $end
$var wire 1 . wSingle $end
$var wire 1 / wTripleByte $end
$var reg 2 0 rD_count [1:0] $end
$var reg 3 1 rD_dstR [2:0] $end
$var reg 5 2 rD_icode [4:0] $end
$var reg 4 3 rD_ifun [3:0] $end
$var reg 3 4 rD_srcR [2:0] $end
$var reg 8 5 rD_valC [7:0] $end
$var reg 14 6 rD_valP [13:0] $end
$var reg 1 7 rD_valid $end
$var reg 3 8 rE_dstR [2:0] $end
$var reg 5 9 rE_icode [4:0] $end
$var reg 4 : rE_ifun [3:0] $end
$var reg 8 ; rE_valC [7:0] $end
$var reg 14 < rE_valP [13:0] $end
$var reg 8 = rE_valS [7:0] $end
$var reg 1 > rE_valid $end
$var reg 8 ? rF1_IR [7:0] $end
$var reg 1 @ rF1_IR_valid $end
$var reg 8 A rF2_IR [7:0] $end
$var reg 1 B rF2_IR_valid $end
$var reg 8 C rF3_IR [7:0] $end
$var reg 1 D rF3_IR_valid $end
$var reg 5 E rM_icode [4:0] $end
$var reg 3 F rStack_ndx [2:0] $end
$upscope $end
$upscope $end
$scope module bench_top $end
$scope module uRom $end
$var wire 14 G ADDR_I [13:0] $end
$var reg 8 H DAT_O [7:0] $end
$upscope $end
$upscope $end
$enddefinitions $end
#0
$dumpvars
bx H
bx G
bx F
bx E
xD
bx C
xB
bx A
x@
bx ?
x>
bx =
bx <
bx ;
bx :
bx 9
bx 8
x7
bx 6
bx 5
bx 4
bx 3
bx 2
bx 1
bx 0
x/
x.
x-
1,
bx +
bx *
bz )
bz (
bz '
bz &
bz %
bz $
0#
1"
0!
$end
#5
07
1@
1!
1#
#10
0!
0#
#15
0>
1B
1!
1#
#20
0!
0#
#25
1D
1!
1#
#30
0!
0#
#35
1!
1#
#40
0!
0#
#45
1!
1#
#50
0!
0#
#55
1!
1#
#60
0!
0#
#65
1!
1#
#70
0!
0#
#75
1!
1#
#80
0!
0#
#85
1!
1#
#90
0!
0#
#95
1!
1#
#100
0!
0#
0"
0,
#105
b1110 H
b1110 +
1.
0-
0/
b0 F
b0 *
b0 G
0B
b0 A
0D
b0 C
b0 0
b0 6
b0 5
b0 4
b0 1
b0 3
b0 2
b0 <
b0 ;
b0 8
b0 :
b0 9
b0 E
0@
b0 ?
1!
1#
#110
0!
0#
#115
1!
1#
#120
0!
0#
#125
1!
1#
#130
0!
0#
#135
1!
1#
#140
0!
0#
#145
1!
1#
#150
0!
0#
#155
1!
1#
#160
0!
0#
#165
1!
1#
#170
0!
0#
#175
1!
1#
#180
0!
0#
#185
1!
1#
#190
0!
0#
#195
1!
1#
#200
0!
0#
1"
1,
#205
b10101010 H
b10101010 +
b1 *
b1 G
b0 =
1@
b1110 ?
1!
1#
#210
0!
0#
#215
b11110 H
b11110 +
b10101010 ?
b111000000000 6
1B
b1110 A
b10 *
b10 G
1!
1#
#220
0!
0#
#225
b1010101 H
b1010101 +
0.
1-
b11 *
b11 G
b10101010 A
1D
b1110 C
b10101000001110 6
b1110 5
b111000000000 <
b11110 ?
1!
1#
#230
0!
0#
#235
b11000001 H
b11000001 +
1.
0-
b1010101 ?
b10101000001110 <
b1110 ;
b1 0
17
b1111010101010 6
b10101010 5
b1 1
b110 4
b1 3
b110 2
b10101010 C
b11110 A
b100 *
b100 G
1!
1#
#240
0!
0#
#245
b10000011 H
b10000011 +
0.
1-
b101 *
b101 G
b1010101 A
b11110 C
07
b0 0
b10101010 =
b1111010101010 <
b10101010 ;
b1 8
b1 :
b110 9
1>
b11000001 ?
1!
1#
#250
0!
0#
#255
b11111111 H
b11111111 +
1.
0-
b10000011 ?
0>
b1 0
17
b101010101 6
b1010101 5
b11 1
b11 3
b1010101 C
b11000001 A
b110 *
b110 G
1!
1#
#260
0!
0#
#265
bx H
bx +
b111 *
b111 G
b10000011 A
b11000001 C
07
b0 0
b1010101 =
b101010101 <
b1010101 ;
b11 8
b11 :
1>
b11111111 ?
1!
1#
#270
0!
0#
#275
bx ?
0>
17
b11111110000011 6
b10000011 5
b0 1
b1 4
b0 3
b11001 2
b10000011 C
b11111111 A
b1000 *
b1000 G
1!
1#
#280
0!
0#
#285
b1001 *
b1001 G
bx A
b11111111 C
bx11111111 6
b11111111 5
b11 4
b10011 2
b0 =
b11111110000011 <
b10000011 ;
b0 8
b0 :
b11001 9
1>
1!
1#
#290
0!
0#
#295
x.
x-
x/
bx11111111 <
b11111111 ;
b10011 9
bx 6
bx 5
b111 1
b111 4
b111 3
b11111 2
bx C
b1010 *
b1010 G
1!
1#
#300
0!
0#
#305
b1011 *
b1011 G
bx 1
bx 4
bx 3
bx 2
bx <
bx ;
b111 8
b111 :
b11111 9
1!
1#
#310
0!
0#
#315
bx =
bx 8
bx :
bx 9
b1100 *
b1100 G
1!
1#
#320
0!
0#
#325
b1101 *
b1101 G
1!
1#
#330
0!
0#
#335
b1110 *
b1110 G
1!
1#
#340
0!
0#
#345
b1111 *
b1111 G
1!
1#
#350
0!
0#
#355
b10000 *
b10000 G
1!
1#
#360
0!
0#
#365
b10001 *
b10001 G
1!
1#
#370
0!
0#
#375
b10010 *
b10010 G
1!
1#
#380
0!
0#
#385
b10011 *
b10011 G
1!
1#
#390
0!
0#
#395
b10100 *
b10100 G
1!
1#
#400
0!
0#
#405
b10101 *
b10101 G
1!
1#
#410
0!
0#
#415
b10110 *
b10110 G
1!
1#
#420
0!
0#
#425
b10111 *
b10111 G
1!
1#
#430
0!
0#
#435
b11000 *
b11000 G
1!
1#
#440
0!
0#
#445
b11001 *
b11001 G
1!
1#
#450
0!
0#
#455
b11010 *
b11010 G
1!
1#
#460
0!
0#
#465
b11011 *
b11011 G
1!
1#
#470
0!
0#
#475
b11100 *
b11100 G
1!
1#
#480
0!
0#
#485
b11101 *
b11101 G
1!
1#
#490
0!
0#
#495
b11110 *
b11110 G
1!
1#
#500
0!
0#
#505
b11111 *
b11111 G
1!
1#
#510
0!
0#
#515
b100000 *
b100000 G
1!
1#
#520
0!
0#
#525
b100001 *
b100001 G
1!
1#
#530
0!
0#
#535
b100010 *
b100010 G
1!
1#
#540
0!
0#
#545
b100011 *
b100011 G
1!
1#
#550
0!
0#
#555
b100100 *
b100100 G
1!
1#
#560
0!
0#
#565
b100101 *
b100101 G
1!
1#
#570
0!
0#
#575
b100110 *
b100110 G
1!
1#
#580
0!
0#
#585
b100111 *
b100111 G
1!
1#
#590
0!
0#
#595
b101000 *
b101000 G
1!
1#
