MCS8/iverilog/cpu_alu.v
// **********
// COPYRIGHT(c) 2018, LUOYIN
// All rights reserved
// 
// IP LIB INDEX	:
// IP Name		: Intel8008
// File Name	: cpu_alu.v
// Module Name	: cpu_alu
// Full Name	: 
// 
// Author		: LUO YIN
// Email		: luoyin1986@gmail.com
// Data			: 2018/04/09
// Version		: 1.0
//
// Abstract		:
// Called By	: 
// 
// Modification Histroy
// 
// **********

// **********
// DEFINE MODEL PORT
// **********
//
module cpu_alu(
	X_I, Y_I, C_I, OP_I,
	E_O, C_O, Z_O, S_O, P_O
);

	// **********
	// DEFINE PARAMETER
	// **********

	// **********
	// DEFINE INPUT
	// **********
	input wire [7:0] X_I;
	input wire [7:0] Y_I;
	input wire C_I;
	input wire [2:0] OP_I;

	// **********
	// DEFINE OUTPUT
	// **********
	output wor [7:0] E_O;
	output wire C_O, Z_O, S_O, P_O;

	// **********
	// ATRRIBUTE
	// **********
	// Adder
	wire [7:0] wAdderE;
	wire wAdderCin;
	wire rAdderCout;
	// Control
	wire wOP_AD, wOP_AC, wOP_SU, wOP_SB, wOP_ND, wOP_XR, wOP_OR, wOP_CP;

	// **********
	// INSTANCE MODULE
	// **********

	// **********
	// MAIN CODE
	// **********
	// Control
	assign wOP_AD = (~OP_I[2])&(~OP_I[1])&(~OP_I[0]);
	assign wOP_AC = (~OP_I[2])&(~OP_I[1])&( OP_I[0]);
	assign wOP_SU = (~OP_I[2])&( OP_I[1])&(~OP_I[0]);
	assign wOP_SB = (~OP_I[2])&( OP_I[1])&( OP_I[0]);
	assign wOP_ND = ( OP_I[2])&(~OP_I[1])&(~OP_I[0]);
	assign wOP_XR = ( OP_I[2])&(~OP_I[1])&( OP_I[0]);
	assign wOP_OR = ( OP_I[2])&( OP_I[1])&(~OP_I[0]);
	assign wOP_CP = ( OP_I[2])&( OP_I[1])&( OP_I[0]);
	
	// Adder
	assign wAdderCin = (wOP_AC|wOP_SB) & C_I;
	assign {wAdderCout, wAdderE} = X_I + (Y_I^{8{wOP_SU|wOP_SB|wOP_CP}}) + (wAdderCin^(wOP_SU|wOP_SB|wOP_CP));
	
	// Output
	assign E_O = ({8{wOP_AD|wOP_AC|wOP_SU|wOP_SB}}&wAdderE) |
				 ({8{wOP_ND}} & (X_I&Y_I)) |
				 ({8{wOP_XR}} & (X_I^Y_I)) |
				 ({8{wOP_OR}} & (X_I|Y_I)) |
				 ({8{wOP_CP}} & X_I);
	assign C_O = (wOP_AC & wAdderCout) | (wOP_SB & (~wAdderCout)) | (wOP_CP & (~wAdderCout));
	assign Z_O = ~(|wAdderE);
	assign S_O = E_O[7];
	assign P_O = ~E_O[0];

endmodule

MCS8/iverilog/bench_cpu_alu.v
// **********
// COPYRIGHT(c) 2018, LUOYIN
// All rights reserved
// 
// IP LIB INDEX	:
// IP Name		:
// File Name	:
// Module Name	:
// Full Name	:
// 
// Author		: 
// Email		:
// Data			:
// Version		:
//
// Abstract		:
// Called By	: 
// 
// Modification Histroy
// 
// **********

`timescale 1us/100ns

// **********
// DEFINE MODEL PORT
// **********
//
module bench_cpu_alu();

	// **********
	// DEFINE PARAMETER
	// **********

	// **********
	// DEFINE INPUT
	// **********

	// **********
	// DEFINE OUTPUT
	// **********

	// **********
	// ATRRIBUTE
	// **********
	reg [7:0] X;
	reg [7:0] Y;
	reg Cin;
	reg [2:0] OP;
	wire [7:0] E;
	wire C, Z, S, P;

	// **********
	// INSTANCE MODULE
	// **********
	cpu_alu uALU(
		.X_I(X), .Y_I(Y), .C_I(Cin), .OP_I(OP),
		.E_O(E), .C_O(C), .Z_O(Z), .S_O(S), .P_O(P)
	);

	// **********
	// MAIN CODE
	// **********
	initial begin
		X <= 8'b10110011;
		Y <= 8'b01101100;
		Cin <= 1'b0;
		OP <= 3'b000;
		#10 OP <= 3'b001;
		#10 OP <= 3'b010;
		#10 OP <= 3'b011;
		#10 OP <= 3'b100;
		#10 OP <= 3'b101;
		#10 OP <= 3'b110;
		#10 OP <= 3'b111;
		#10 $finish;
		end
		
	initial begin
		$dumpvars(0, uALU);
		end

endmodule

MCS8/iverilog/dump.vcd
$date
	Mon Apr  9 13:37:39 2018
$end
$version
	Icarus Verilog
$end
$timescale
	100ns
$end
$scope module bench_cpu_alu $end
$scope module uALU $end
$var wire 1 ! C_I $end
$var wire 1 " C_O $end
$var wire 8 # E_O [7:0] $end
$var wire 3 $ OP_I [2:0] $end
$var wire 1 % P_O $end
$var wire 1 & S_O $end
$var wire 8 ' X_I [7:0] $end
$var wire 8 ( Y_I [7:0] $end
$var wire 1 ) Z_O $end
$var wire 1 * wAdderCin $end
$var wire 1 + wAdderCout $end
$var wire 8 , wAdderE [7:0] $end
$var wire 1 - wOP_AC $end
$var wire 1 . wOP_AD $end
$var wire 1 / wOP_CP $end
$var wire 1 0 wOP_ND $end
$var wire 1 1 wOP_OR $end
$var wire 1 2 wOP_SB $end
$var wire 1 3 wOP_SU $end
$var wire 1 4 wOP_XR $end
$upscope $end
$upscope $end
$enddefinitions $end
#0
$dumpvars
04
03
02
01
00
0/
1.
0-
b11111 ,
1+
0*
0)
b1101100 (
b10110011 '
0&
0%
b0 $
b11111 #
0"
0!
$end
#100
1"
0.
1-
b1 $
#200
b1000111 #
b1000111 ,
0"
0.
13
0-
b10 $
#300
03
12
b11 $
#400
1%
b100000 #
b11111 ,
10
02
b100 $
#500
0%
1&
b11011111 #
00
14
b101 $
#600
b11111111 #
00
11
04
b110 $
#700
b10110011 #
b1000111 ,
01
1/
b111 $
