MCS8/iverilog/clock.v
// **********
// COPYRIGHT(c) 2018, LUOYIN
// All rights reserved
// 
// IP LIB INDEX	:
// IP Name		: clock
// File Name	: clock.v
// Module Name	: clock
// Full Name	: clock generator for clk1 and clk2
// 
// Author		: LUO YIN
// Email		: luoyin1986@gmail.com
// Data			: 2018/04/03
// Version		: 1.0
//
// Abstract		: 
// Called By	: bench_top
// 
// Modification Histroy
// 
// **********
`timescale 1us/100ns

// **********
// DEFINE MODEL PORT
// **********
//
module clock(CLK_I, nRST_I, CLK1_O, CLK2_O);

	// **********
	// DEFINE PARAMETER
	// **********

	// **********
	// DEFINE INPUT
	// **********
	input wire CLK_I;
	input wire nRST_I;

	// **********
	// DEFINE OUTPUT
	// **********
	output wire CLK1_O;
	output wire CLK2_O;

	// **********
	// ATRRIBUTE
	// **********
	reg [1:0] rCount;

	// **********
	// INSTANCE MODULE
	// **********
	assign CLK1_O=(~rCount[1])&( rCount[0]);
	assign CLK2_O=( rCount[1])&( rCount[0]);

	// **********
	// MAIN CODE
	// **********
	initial begin
		rCount<=2'b00;
	end

	always @(posedge CLK_I) begin
		if(~nRST_I)
			rCount<=2'b00;
		else
			rCount<=rCount+1;
	end
	
endmodule

MCS8/iverilog/bench_clock.v
`timescale 1us/100ns

module bench_clock(CLK_O, nRST_O);

	output reg CLK_O;
	output reg nRST_O;

	initial begin
		CLK_O=1'b0;
		nRST_O=1'b1;
		forever #5 CLK_O=~CLK_O;
	end
	
	initial begin
		#2000 $finish;
	end

endmodule

MCS8/iverilog/bench_top.v
`timescale 1us/100ns

module bench_top;

	wire CLK, nRST, CLK1, CLK2;

	bench_clock #(.HALF_CYCLE(5)) uClockGen(.CLK_O(CLK), .nRST_O(nRST));
	clock uClock(.CLK_I(CLK), .nRST_I(nRST), .CLK1_O(CLK1), .CLK2_O(CLK2));
	
	initial begin
		$dumpvars(0, uClockGen);
		$dumpvars(0, uClock);
	end

endmodule

MCS8/iverilog/dump.vcd
$date
	Tue Apr  3 14:02:32 2018
$end
$version
	Icarus Verilog
$end
$timescale
	100ns
$end
$scope module bench_top $end
$scope module uClockGen $end
$var reg 1 ! CLK_O $end
$var reg 1 " nRST_O $end
$upscope $end
$upscope $end
$scope module bench_top $end
$scope module uClock $end
$var wire 1 # CLK1_O $end
$var wire 1 $ CLK2_O $end
$var wire 1 % CLK_I $end
$var wire 1 & nRST_I $end
$var reg 2 ' rCount [1:0] $end
$upscope $end
$upscope $end
$enddefinitions $end
#0
$dumpvars
b0 '
1&
0%
0$
0#
1"
0!
$end
#50
1#
b1 '
1!
1%
#100
0!
0%
#150
0#
b10 '
1!
1%
#200
0!
0%
#250
1$
b11 '
1!
1%
#300
0!
0%
#350
0$
b0 '
1!
1%
#400
0!
0%
#450
1#
b1 '
1!
1%
#500
0!
0%
#550
0#
b10 '
1!
1%
#600
0!
0%
#650
1$
b11 '
1!
1%
#700
0!
0%
#750
0$
b0 '
1!
1%
#800
0!
0%
#850
1#
b1 '
1!
1%
#900
0!
0%
#950
0#
b10 '
1!
1%
#1000
0!
0%
0"
0&
#1050
b0 '
1!
1%
#1100
0!
0%
#1150
1!
1%
#1200
0!
0%
#1250
1!
1%
#1300
0!
0%
#1350
1!
1%
#1400
0!
0%
#1450
1!
1%
#1500
0!
0%
#1550
1!
1%
#1600
0!
0%
#1650
1!
1%
#1700
0!
0%
#1750
1!
1%
#1800
0!
0%
#1850
1!
1%
#1900
0!
0%
#1950
1!
1%
#2000
0!
0%
#2050
1!
1%
#2100
0!
0%
#2150
1!
1%
#2200
0!
0%
#2250
1!
1%
#2300
0!
0%
#2350
1!
1%
#2400
0!
0%
#2450
1!
1%
#2500
0!
0%
#2550
1!
1%
#2600
0!
0%
#2650
1!
1%
#2700
0!
0%
#2750
1!
1%
#2800
0!
0%
#2850
1!
1%
#2900
0!
0%
#2950
1!
1%
#3000
0!
0%
1"
1&
#3050
1#
b1 '
1!
1%
#3100
0!
0%
#3150
0#
b10 '
1!
1%
#3200
0!
0%
#3250
1$
b11 '
1!
1%
#3300
0!
0%
#3350
0$
b0 '
1!
1%
#3400
0!
0%
#3450
1#
b1 '
1!
1%
#3500
0!
0%
#3550
0#
b10 '
1!
1%
#3600
0!
0%
#3650
1$
b11 '
1!
1%
#3700
0!
0%
#3750
0$
b0 '
1!
1%
#3800
0!
0%
#3850
1#
b1 '
1!
1%
#3900
0!
0%
#3950
0#
b10 '
1!
1%
#4000
0!
0%
#4050
1$
b11 '
1!
1%
#4100
0!
0%
#4150
0$
b0 '
1!
1%
#4200
0!
0%
#4250
1#
b1 '
1!
1%
#4300
0!
0%
#4350
0#
b10 '
1!
1%
#4400
0!
0%
#4450
1$
b11 '
1!
1%
#4500
0!
0%
#4550
0$
b0 '
1!
1%
#4600
0!
0%
#4650
1#
b1 '
1!
1%
#4700
0!
0%
#4750
0#
b10 '
1!
1%
#4800
0!
0%
#4850
1$
b11 '
1!
1%
#4900
0!
0%
#4950
0$
b0 '
1!
1%
#5000
0!
0%
#5050
1#
b1 '
1!
1%
#5100
0!
0%
#5150
0#
b10 '
1!
1%
#5200
0!
0%
#5250
1$
b11 '
1!
1%
#5300
0!
0%
#5350
0$
b0 '
1!
1%
#5400
0!
0%
#5450
1#
b1 '
1!
1%
#5500
0!
0%
#5550
0#
b10 '
1!
1%
#5600
0!
0%
#5650
1$
b11 '
1!
1%
#5700
0!
0%
#5750
0$
b0 '
1!
1%
#5800
0!
0%
#5850
1#
b1 '
1!
1%
#5900
0!
0%
#5950
0#
b10 '
1!
1%
#6000
0!
0%
#6050
1$
b11 '
1!
1%
#6100
0!
0%
#6150
0$
b0 '
1!
1%
#6200
0!
0%
#6250
1#
b1 '
1!
1%
#6300
0!
0%
#6350
0#
b10 '
1!
1%
#6400
0!
0%
#6450
1$
b11 '
1!
1%
#6500
0!
0%
#6550
0$
b0 '
1!
1%
#6600
0!
0%
#6650
1#
b1 '
1!
1%
#6700
0!
0%
#6750
0#
b10 '
1!
1%
#6800
0!
0%
#6850
1$
b11 '
1!
1%
#6900
0!
0%
#6950
0$
b0 '
1!
1%
#7000
0!
0%
#7050
1#
b1 '
1!
1%
#7100
0!
0%
#7150
0#
b10 '
1!
1%
#7200
0!
0%
#7250
1$
b11 '
1!
1%
#7300
0!
0%
#7350
0$
b0 '
1!
1%
#7400
0!
0%
#7450
1#
b1 '
1!
1%
#7500
0!
0%
#7550
0#
b10 '
1!
1%
#7600
0!
0%
#7650
1$
b11 '
1!
1%
#7700
0!
0%
#7750
0$
b0 '
1!
1%
#7800
0!
0%
#7850
1#
b1 '
1!
1%
#7900
0!
0%
#7950
0#
b10 '
1!
1%
#8000
0!
0%
#8050
1$
b11 '
1!
1%
#8100
0!
0%
#8150
0$
b0 '
1!
1%
#8200
0!
0%
#8250
1#
b1 '
1!
1%
#8300
0!
0%
#8350
0#
b10 '
1!
1%
#8400
0!
0%
#8450
1$
b11 '
1!
1%
#8500
0!
0%
#8550
0$
b0 '
1!
1%
#8600
0!
0%
#8650
1#
b1 '
1!
1%
#8700
0!
0%
#8750
0#
b10 '
1!
1%
#8800
0!
0%
#8850
1$
b11 '
1!
1%
#8900
0!
0%
#8950
0$
b0 '
1!
1%
#9000
0!
0%
#9050
1#
b1 '
1!
1%
#9100
0!
0%
#9150
0#
b10 '
1!
1%
#9200
0!
0%
#9250
1$
b11 '
1!
1%
#9300
0!
0%
#9350
0$
b0 '
1!
1%
#9400
0!
0%
#9450
1#
b1 '
1!
1%
#9500
0!
0%
#9550
0#
b10 '
1!
1%
#9600
0!
0%
#9650
1$
b11 '
1!
1%
#9700
0!
0%
#9750
0$
b0 '
1!
1%
#9800
0!
0%
#9850
1#
b1 '
1!
1%
#9900
0!
0%
#9950
0#
b10 '
1!
1%
#10000
0!
0%
#10050
1$
b11 '
1!
1%
#10100
0!
0%
#10150
0$
b0 '
1!
1%
#10200
0!
0%
#10250
1#
b1 '
1!
1%
#10300
0!
0%
#10350
0#
b10 '
1!
1%
#10400
0!
0%
#10450
1$
b11 '
1!
1%
#10500
0!
0%
#10550
0$
b0 '
1!
1%
#10600
0!
0%
#10650
1#
b1 '
1!
1%
#10700
0!
0%
#10750
0#
b10 '
1!
1%
#10800
0!
0%
#10850
1$
b11 '
1!
1%
#10900
0!
0%
#10950
0$
b0 '
1!
1%
#11000
0!
0%
#11050
1#
b1 '
1!
1%
#11100
0!
0%
#11150
0#
b10 '
1!
1%
#11200
0!
0%
#11250
1$
b11 '
1!
1%
#11300
0!
0%
#11350
0$
b0 '
1!
1%
#11400
0!
0%
#11450
1#
b1 '
1!
1%
#11500
0!
0%
#11550
0#
b10 '
1!
1%
#11600
0!
0%
#11650
1$
b11 '
1!
1%
#11700
0!
0%
#11750
0$
b0 '
1!
1%
#11800
0!
0%
#11850
1#
b1 '
1!
1%
#11900
0!
0%
#11950
0#
b10 '
1!
1%
#12000
0!
0%
#12050
1$
b11 '
1!
1%
#12100
0!
0%
#12150
0$
b0 '
1!
1%
#12200
0!
0%
#12250
1#
b1 '
1!
1%
#12300
0!
0%
#12350
0#
b10 '
1!
1%
#12400
0!
0%
#12450
1$
b11 '
1!
1%
#12500
0!
0%
#12550
0$
b0 '
1!
1%
#12600
0!
0%
#12650
1#
b1 '
1!
1%
#12700
0!
0%
#12750
0#
b10 '
1!
1%
#12800
0!
0%
#12850
1$
b11 '
1!
1%
#12900
0!
0%
#12950
0$
b0 '
1!
1%
#13000
0!
0%
#13050
1#
b1 '
1!
1%
#13100
0!
0%
#13150
0#
b10 '
1!
1%
#13200
0!
0%
#13250
1$
b11 '
1!
1%
#13300
0!
0%
#13350
0$
b0 '
1!
1%
#13400
0!
0%
#13450
1#
b1 '
1!
1%
#13500
0!
0%
#13550
0#
b10 '
1!
1%
#13600
0!
0%
#13650
1$
b11 '
1!
1%
#13700
0!
0%
#13750
0$
b0 '
1!
1%
#13800
0!
0%
#13850
1#
b1 '
1!
1%
#13900
0!
0%
#13950
0#
b10 '
1!
1%
#14000
0!
0%
#14050
1$
b11 '
1!
1%
#14100
0!
0%
#14150
0$
b0 '
1!
1%
#14200
0!
0%
#14250
1#
b1 '
1!
1%
#14300
0!
0%
#14350
0#
b10 '
1!
1%
#14400
0!
0%
#14450
1$
b11 '
1!
1%
#14500
0!
0%
#14550
0$
b0 '
1!
1%
#14600
0!
0%
#14650
1#
b1 '
1!
1%
#14700
0!
0%
#14750
0#
b10 '
1!
1%
#14800
0!
0%
#14850
1$
b11 '
1!
1%
#14900
0!
0%
#14950
0$
b0 '
1!
1%
#15000
0!
0%
#15050
1#
b1 '
1!
1%
#15100
0!
0%
#15150
0#
b10 '
1!
1%
#15200
0!
0%
#15250
1$
b11 '
1!
1%
#15300
0!
0%
#15350
0$
b0 '
1!
1%
#15400
0!
0%
#15450
1#
b1 '
1!
1%
#15500
0!
0%
#15550
0#
b10 '
1!
1%
#15600
0!
0%
#15650
1$
b11 '
1!
1%
#15700
0!
0%
#15750
0$
b0 '
1!
1%
#15800
0!
0%
#15850
1#
b1 '
1!
1%
#15900
0!
0%
#15950
0#
b10 '
1!
1%
#16000
0!
0%
#16050
1$
b11 '
1!
1%
#16100
0!
0%
#16150
0$
b0 '
1!
1%
#16200
0!
0%
#16250
1#
b1 '
1!
1%
#16300
0!
0%
#16350
0#
b10 '
1!
1%
#16400
0!
0%
#16450
1$
b11 '
1!
1%
#16500
0!
0%
#16550
0$
b0 '
1!
1%
#16600
0!
0%
#16650
1#
b1 '
1!
1%
#16700
0!
0%
#16750
0#
b10 '
1!
1%
#16800
0!
0%
#16850
1$
b11 '
1!
1%
#16900
0!
0%
#16950
0$
b0 '
1!
1%
#17000
0!
0%
#17050
1#
b1 '
1!
1%
#17100
0!
0%
#17150
0#
b10 '
1!
1%
#17200
0!
0%
#17250
1$
b11 '
1!
1%
#17300
0!
0%
#17350
0$
b0 '
1!
1%
#17400
0!
0%
#17450
1#
b1 '
1!
1%
#17500
0!
0%
#17550
0#
b10 '
1!
1%
#17600
0!
0%
#17650
1$
b11 '
1!
1%
#17700
0!
0%
#17750
0$
b0 '
1!
1%
#17800
0!
0%
#17850
1#
b1 '
1!
1%
#17900
0!
0%
#17950
0#
b10 '
1!
1%
#18000
0!
0%
#18050
1$
b11 '
1!
1%
#18100
0!
0%
#18150
0$
b0 '
1!
1%
#18200
0!
0%
#18250
1#
b1 '
1!
1%
#18300
0!
0%
#18350
0#
b10 '
1!
1%
#18400
0!
0%
#18450
1$
b11 '
1!
1%
#18500
0!
0%
#18550
0$
b0 '
1!
1%
#18600
0!
0%
#18650
1#
b1 '
1!
1%
#18700
0!
0%
#18750
0#
b10 '
1!
1%
#18800
0!
0%
#18850
1$
b11 '
1!
1%
#18900
0!
0%
#18950
0$
b0 '
1!
1%
#19000
0!
0%
#19050
1#
b1 '
1!
1%
#19100
0!
0%
#19150
0#
b10 '
1!
1%
#19200
0!
0%
#19250
1$
b11 '
1!
1%
#19300
0!
0%
#19350
0$
b0 '
1!
1%
#19400
0!
0%
#19450
1#
b1 '
1!
1%
#19500
0!
0%
#19550
0#
b10 '
1!
1%
#19600
0!
0%
#19650
1$
b11 '
1!
1%
#19700
0!
0%
#19750
0$
b0 '
1!
1%
#19800
0!
0%
#19850
1#
b1 '
1!
1%
#19900
0!
0%
#19950
0#
b10 '
1!
1%
